{"1":[{"n":1,"w":"וַ/יְהִי","t":"va/y.Hi","g":"and it was","s":"H9001","m":"Hc/Vqw3ms","l":"ו","lg":"&/H1961=הָיָה=to be"},{"n":2,"w":"מִ/יָּמִים","t":"mi./ya.Mim","g":"from days","s":"H9006","m":"HR/Ncmpa","l":"מ","lg":"from/H3117G=יוֹם=: day"},{"n":3,"w":"רַבִּים","t":"ra.Bim","g":"many","s":"H7227A","m":"HAampa","l":"רַב","lg":"many"},{"n":4,"w":"אַחֲרֵי","t":"'A.cha.rei","g":"after","s":"H0310A","m":"HAcmpc","l":"אַחַר","lg":"after"},{"n":5,"w":"אֲשֶׁר\\","t":"'a.Sher-","g":"that","s":"H0834A\\H9014","m":"HTr","l":"אֲשֶׁר","lg":"which\\H9014=־=link"},{"n":6,"w":"הֵנִיחַ","t":"he.Ni.ach","g":"he had given rest","s":"H5117","m":"HVhp3ms","l":"נוּחַ","lg":"to rest"},{"n":7,"w":"יְהוָה","t":"Yah.weh","g":"Yahweh","s":"H3068G","m":"HNpt","l":"יהוה","lg":"LORD"},{"n":8,"w":"לְ/יִשְׂרָאֵל","t":"le./Yis.ra.'El","g":"to Israel","s":"H9005","m":"HR/Npl","l":"ל","lg":"to/H3478=יִשְׂרָאֵל=Israel"},{"n":9,"w":"מִ/כָּל\\","t":"mi./kol","g":"from all","s":"H9006","m":"HR/Ncmsc","l":"מ","lg":"from/H3605=כֹּל=all\\H9014=־=link"},{"n":10,"w":"אֹיְבֵי/הֶם","t":"'o.ye.vei./Hem","g":"enemies their","s":"H0341","m":"HVqrmpc/Sp3mp","l":"אֹיֵב","lg":"enemy/H9028=Pp3m=their"},{"n":11,"w":"מִ/סָּבִיב","t":"mi./sa.Viv","g":"from round about","s":"H9006","m":"HR/Ncbsa","l":"מ","lg":"from/H5439G=סָבִיב=: around"},{"n":12,"w":"וִ/יהוֹשֻׁעַ","t":"vi./ho.Shu.a'","g":"and Joshua","s":"H9002","m":"HC/Npm","l":"ו","lg":"and/H3091G=יְהוֹשׁוּעַ=Joshua"},{"n":13,"w":"זָקֵן","t":"za.Ken","g":"he was old","s":"H2204","m":"HVqp3ms","l":"זָקֵן","lg":"be old"},{"n":14,"w":"בָּא","t":"ba'","g":"he had come","s":"H0935J","m":"HVqp3ms","l":"בּוֹא","lg":": advanced"},{"n":15,"w":"בַּ/יָּמִים\\","t":"ba/i.ya.Mim","g":"in <the> days","s":"H9003","m":"HRd/Ncmpa","l":"ב","lg":"in/H3117I=יוֹם=: year[of_days]"}],"2":[{"n":1,"w":"וַ/יִּקְרָא","t":"va/i.yik.Ra'","g":"and he summoned","s":"H9001","m":"Hc/Vqw3ms","l":"ו","lg":"&/H7121G=קָרָא=: call_to"},{"n":2,"w":"יְהוֹשֻׁעַ","t":"ye.ho.Shu.a'","g":"Joshua","s":"H3091G","m":"HNpm","l":"יְהוֹשׁוּעַ","lg":"Joshua"},{"n":3,"w":"לְ/כָל\\","t":"le./khol","g":"<to> all","s":"H9005","m":"HR/Ncmsc","l":"ל","lg":"to/H3605=כֹּל=all\\H9014=־=link"},{"n":4,"w":"יִשְׂרָאֵל","t":"Yis.ra.'El","g":"Israel","s":"H3478","m":"HNpl","l":"יִשְׂרָאֵל","lg":"Israel"},{"n":5,"w":"לִ/זְקֵנָי/ו","t":"li/z.ke.Na/v","g":"<to> elders its","s":"H9005","m":"HR/Aampc/Sp3ms","l":"ל","lg":"to/H2205G=זָקֵן=: elder"},{"n":6,"w":"וּ/לְ/רָאשָׁי/ו","t":"u./le./ra.Sha/v","g":"and <to> leaders its","s":"H9002","m":"HC/R/Ncmpc/Sp3ms","l":"ו","lg":"and/H9005=ל=to/H7218H=רֹאשׁ=: leader"},{"n":7,"w":"וּ/לְ/שֹׁפְטָי/ו","t":"u./le./sho.fe.Ta/v","g":"and <to> judges its","s":"H9002","m":"HC/R/Vqrmpc/Sp3ms","l":"ו","lg":"and/H9005=ל=to/H8199=שָׁפַט=to judge/H9033=Os3m=him"},{"n":8,"w":"וּ/לְ/שֹׁטְרָי/ו","t":"u./le./sho.te.Ra/v","g":"and <to> officials its","s":"H9002","m":"HC/R/Vqrmpc/Sp3ms","l":"ו","lg":"and/H9005=ל=to/H7860=שֹׁטֵר=official/H9023=Ps3m=his"},{"n":9,"w":"וַ/יֹּאמֶר","t":"va/i.Yo.mer","g":"and he said","s":"H9001","m":"Hc/Vqw3ms","l":"ו","lg":"&/H0559=אָמַר=to say"},{"n":10,"w":"אֲלֵ/הֶם","t":"'a.le./Hem","g":"to them","s":"H0413","m":"HRd/Sp3mp","l":"אֶל","lg":"to(wards)/H9038=Op3m=them"},{"n":11,"w":"אֲנִי","t":"'a.Ni","g":"I","s":"H0589","m":"HPp1bs","l":"אֲנִי","lg":""},{"n":12,"w":"זָקַנְתִּי","t":"za.Kan.ti","g":"I am old","s":"H2204","m":"HVqp1cs","l":"זָקֵן","lg":"be old"},{"n":13,"w":"בָּאתִי","t":"Ba.ti","g":"I have come","s":"H0935J","m":"HVqp1cs","l":"בּוֹא","lg":": advanced"},{"n":14,"w":"בַּ/יָּמִים\\","t":"ba/i.ya.Mim","g":"in <the> days","s":"H9003","m":"HRd/Ncmpa","l":"ב","lg":"in/H3117I=יוֹם=: year[of_days]"}],"3":[{"n":1,"w":"וְ/אַתֶּם","t":"ve./'a.Tem","g":"and you","s":"H9002","m":"HC/Pp2mp","l":"ו","lg":"and/H0859D=אַתֶּם=you(m.p.)"},{"n":2,"w":"רְאִיתֶם","t":"re.'i.Tem","g":"you have seen","s":"H7200G","m":"HVqp2mp","l":"רָאָה","lg":": see"},{"n":3,"w":"אֵת","t":"'et","g":"<obj.>","s":"H0853","m":"HTo","l":"אֵת","lg":"[Obj.]"},{"n":4,"w":"כָּל\\","t":"kol-","g":"all","s":"H3605\\H9014","m":"HNcmsa","l":"כֹּל","lg":"all\\H9014=־=link"},{"n":5,"w":"אֲשֶׁר","t":"'a.Sher","g":"that","s":"H0834A","m":"HTr","l":"אֲשֶׁר","lg":"which"},{"n":6,"w":"עָשָׂה","t":"'a.Sah","g":"he has done","s":"H6213A","m":"HVqp3ms","l":"עָשָׂה","lg":": do"},{"n":7,"w":"יְהוָה","t":"Yah.weh","g":"Yahweh","s":"H3068G","m":"HNpt","l":"יהוה","lg":"LORD"},{"n":8,"w":"אֱלֹהֵי/כֶם","t":"'e.lo.hei./Khem","g":"God your","s":"H0430G","m":"HNcmpc/Sp2mp","l":"אֱלֹהִים","lg":"God"},{"n":9,"w":"לְ/כָל\\","t":"le./khol","g":"to all","s":"H9005","m":"HR/Ncmsc","l":"ל","lg":"to/H3605=כֹּל=all\\H9014=־=link"},{"n":10,"w":"הַ/גּוֹיִם","t":"ha./go.Yim","g":"the nations","s":"H9009","m":"HTd/Ncmpa","l":"ה","lg":"the/H1471A=גּוֹי=nation"},{"n":11,"w":"הָ/אֵלֶּה","t":"ha./'E.leh","g":"<the> these","s":"H9009","m":"HTd/Tm","l":"ה","lg":"the/H0428=אֵ֫לֶּה=these"},{"n":12,"w":"מִ/פְּנֵי/כֶם","t":"mi./pe.nei./Khem","g":"from before you","s":"H9006","m":"HR/Ncmpc/Sp2mp","l":"מ","lg":"from/H6440G=פָּנֶה=: before"},{"n":13,"w":"כִּי","t":"ki","g":"for","s":"H3588A","m":"HTc","l":"כִּי","lg":"for"},{"n":14,"w":"יְהוָה","t":"Yah.weh","g":"Yahweh","s":"H3068G","m":"HNpt","l":"יהוה","lg":"LORD"},{"n":15,"w":"אֱלֹהֵי/כֶם","t":"'e.lo.hei./Khem","g":"God your","s":"H0430G","m":"HNcmpc/Sp2mp","l":"אֱלֹהִים","lg":"God"},{"n":16,"w":"הוּא","t":"hu'","g":"he","s":"H1931","m":"HPp3ms","l":"הוּא","lg":"he;_she;_it"},{"n":17,"w":"הַ/נִּלְחָם","t":"ha./nil.Cham","g":"[is] the [one who] has been fighting","s":"H9009","m":"HTd/VNrmsa","l":"ה","lg":"the/H3898A=לָחַם=to fight"},{"n":18,"w":"לָ/כֶם\\","t":"la./Khem","g":"for <the> you","s":"H9005","m":"HRd/Sp2mp","l":"ל","lg":"to/H9036=Op2m=you\\H9016=׃=verseEnd"}],"4":[{"n":1,"w":"רְאוּ","t":"re.'U","g":"see","s":"H7200I","m":"HVqv2mp","l":"רָאָה","lg":": behold!"},{"n":2,"w":"הִפַּלְתִּי","t":"hi.Pal.ti","g":"I have made fall","s":"H5307I","m":"HVhp1cs","l":"נָפַל","lg":": allot"},{"n":3,"w":"לָ/כֶם","t":"la./Khem","g":"to <the> you","s":"H9005","m":"HRd/Sp2mp","l":"ל","lg":"to/H9036=Op2m=you"},{"n":4,"w":"אֶת\\","t":"'et-","g":"<obj.>","s":"H0853\\H9014","m":"HTo","l":"אֵת","lg":"[Obj.]\\H9014=־=link"},{"n":5,"w":"הַ/גּוֹיִם","t":"Ha./go.yim","g":"the nations","s":"H9009","m":"HTd/Ncmpa","l":"ה","lg":"the/H1471A=גּוֹי=nation"},{"n":6,"w":"הַ/נִּשְׁאָרִים","t":"ha./nish.'a.Rim","g":"which remain","s":"H9009","m":"HTd/VNrmpa","l":"ה","lg":"the/H7604=שָׁאַר=to remain"},{"n":7,"w":"הָ/אֵלֶּה","t":"ha./'E.leh","g":"<the> these","s":"H9009","m":"HTd/Tm","l":"ה","lg":"the/H0428=אֵ֫לֶּה=these"},{"n":8,"w":"בְּ/נַחֲלָה","t":"be./na.cha.Lah","g":"<in> an inheritance","s":"H9003","m":"HR/Ncfsa","l":"ב","lg":"in/H5159=נַחֲלָה=inheritance"},{"n":9,"w":"לְ/שִׁבְטֵי/כֶם","t":"le./shiv.tei./Khem","g":"for tribes your","s":"H9005","m":"HR/Ncmpc/Sp2mp","l":"ל","lg":"to/H7626H=שֵׁ֫בֶט=: tribe"},{"n":10,"w":"מִן\\","t":"min-","g":"from","s":"H4480A\\H9014","m":"HR","l":"מִן־","lg":"from\\H9014=־=link"},{"n":11,"w":"הַ/יַּרְדֵּן","t":"hai./yar.Den","g":"the Jordan","s":"H9009","m":"HTd/Npl","l":"ה","lg":"the/H3383=יַרְדֵּן=Jordan"},{"n":12,"w":"וְ/כָל\\","t":"ve./khol","g":"and all","s":"H9002","m":"HC/Ncmsc","l":"ו","lg":"and/H3605=כֹּל=all\\H9014=־=link"},{"n":13,"w":"הַ/גּוֹיִם","t":"ha./go.Yim","g":"the nations","s":"H9009","m":"HTd/Ncmpa","l":"ה","lg":"the/H1471A=גּוֹי=nation"},{"n":14,"w":"אֲשֶׁר","t":"'a.Sher","g":"which","s":"H0834A","m":"HTr","l":"אֲשֶׁר","lg":"which"},{"n":15,"w":"הִכְרַתִּי","t":"hikh.Ra.ti","g":"I have cut off","s":"H3772I","m":"HVhp1cs","l":"כָּרַת","lg":": eliminate"},{"n":16,"w":"וְ/הַ/יָּם","t":"ve./hai./Yam","g":"and the sea","s":"H9002","m":"HC/Td/Ncmsa","l":"ו","lg":"and/H9009=ה=the/H3220G=יָם=: sea"},{"n":17,"w":"הַ/גָּדוֹל","t":"ha./ga.Dol","g":"<the> great","s":"H9009","m":"HTd/Aamsa","l":"ה","lg":"the/H1419J=גָּדוֹל=Great( Sea) (KJV: the great sea; NIV: Mediterranean Sea)"},{"n":18,"w":"מְבוֹא","t":"me.Vo'","g":"[the] setting of","s":"H3996","m":"HNcmsc","l":"מָבוֹא","lg":"entrance"},{"n":19,"w":"הַ/שָּׁמֶשׁ\\","t":"ha./Sha.mesh","g":"the sun","s":"H9009","m":"HTd/Ncbsa","l":"ה","lg":"the/H8121=שֶׁ֫מֶשׁ=sun\\H9016=׃=verseEnd"}],"5":[{"n":1,"w":"וַ/יהוָה","t":"va./Yah.weh","g":"and Yahweh","s":"H9002","m":"HC/Npt","l":"ו","lg":"and/H3068G=יהוה=LORD"},{"n":2,"w":"אֱלֹהֵי/כֶם","t":"'e.lo.hei./Khem","g":"God your","s":"H0430G","m":"HNcmpc/Sp2mp","l":"אֱלֹהִים","lg":"God"},{"n":3,"w":"הוּא","t":"hu'","g":"he","s":"H1931","m":"HPp3ms","l":"הוּא","lg":"he;_she;_it"},{"n":4,"w":"יֶהְדֳּפֵ/ם","t":"yeh.do.Fe/m","g":"he will drive out them","s":"H1920","m":"HVqi3ms/Sp3mp","l":"הָדַף","lg":"to thrust/H9038=Op3m=them"},{"n":5,"w":"מִ/פְּנֵי/כֶם","t":"mi./pe.nei./Khem","g":"from before you","s":"H9006","m":"HR/Ncmpc/Sp2mp","l":"מ","lg":"from/H6440G=פָּנֶה=: before"},{"n":6,"w":"וְ/הוֹרִישׁ","t":"ve./ho.Rish","g":"and he will dispossess","s":"H9001","m":"Hc/Vhq3ms","l":"ו","lg":"&/H3423H=יָרַשׁ=: take"},{"n":7,"w":"אֹתָ/ם","t":"'o.Ta/m","g":"<obj.> them","s":"H0853","m":"HTo/Sp3mp","l":"אֵת","lg":"[Obj.]/H9038=Op3m=them"},{"n":8,"w":"מִ/לִּ/פְנֵי/כֶם","t":"mi./li/f.nei./Khem","g":"from to before you","s":"H9006","m":"HR/R/Ncmpc/Sp2mp","l":"מ","lg":"from/H9005=ל=to/H6440G=פָּנֶה=: before"},{"n":9,"w":"וִ/ירִשְׁתֶּם","t":"vi./rish.Tem","g":"and you will take possession of","s":"H9001","m":"Hc/Vqq2mp","l":"ו","lg":"&/H3423H=יָרַשׁ=: take"},{"n":10,"w":"אֶת\\","t":"'et-","g":"<obj.>","s":"H0853\\H9014","m":"HTo","l":"אֵת","lg":"[Obj.]\\H9014=־=link"},{"n":11,"w":"אַרְצָ/ם","t":"'ar.Tza/m","g":"land their","s":"H0776G","m":"HNcfsc/Sp3mp","l":"אֶ֫רֶץ","lg":": country;_planet"},{"n":12,"w":"כַּ/אֲשֶׁר","t":"ka./'a.Sher","g":"just as","s":"H9004","m":"HR/Tr","l":"כ","lg":"like/H0834D=כַּאֲשֶׁר=as which"},{"n":13,"w":"דִּבֶּר","t":"di.Ber","g":"he spoke","s":"H1696I","m":"HVpp3ms","l":"דָבַר","lg":": promise"},{"n":14,"w":"יְהוָה","t":"Yah.weh","g":"Yahweh","s":"H3068G","m":"HNpt","l":"יהוה","lg":"LORD"},{"n":15,"w":"אֱלֹהֵי/כֶם","t":"'e.lo.hei./Khem","g":"God your","s":"H0430G","m":"HNcmpc/Sp2mp","l":"אֱלֹהִים","lg":"God"},{"n":16,"w":"לָ/כֶם\\","t":"la./Khem","g":"to <the> you","s":"H9005","m":"HRd/Sp2mp","l":"ל","lg":"to/H9036=Op2m=you\\H9016=׃=verseEnd"}],"6":[{"n":1,"w":"וַ/חֲזַקְתֶּם","t":"va./cha.zak.Tem","g":"and you will be strong","s":"H9001","m":"Hc/Vqq2mp","l":"ו","lg":"&/H2388G=חָזַק=: strengthen"},{"n":2,"w":"מְאֹד","t":"me.'Od","g":"very","s":"H3966","m":"HAcmsa","l":"מְאֹד","lg":"much"},{"n":3,"w":"לִ/שְׁמֹר","t":"li/sh.Mor","g":"to take care","s":"H9005","m":"HR/Vqcc","l":"ל","lg":"to/H8104G=שָׁמַר=: obey"},{"n":4,"w":"וְ/לַ/עֲשׂוֹת","t":"ve./la./'a.Sot","g":"and to do","s":"H9002","m":"HC/R/Vqcc","l":"ו","lg":"and/H9005=ל=to/H6213A=עָשָׂה=: do"},{"n":5,"w":"אֵת","t":"'et","g":"<obj.>","s":"H0853","m":"HTo","l":"אֵת","lg":"[Obj.]"},{"n":6,"w":"כָּל\\","t":"kol-","g":"every","s":"H3605\\H9014","m":"HNcmsa","l":"כֹּל","lg":"all\\H9014=־=link"},{"n":7,"w":"הַ/כָּתוּב","t":"ha./ka.Tuv","g":"<the> [thing] written","s":"H9009","m":"HTd/Vqsmsa","l":"ה","lg":"the/H3789=כָּתַב=to write"},{"n":8,"w":"בְּ/סֵפֶר","t":"be./Se.fer","g":"in [the] book of","s":"H9003","m":"HR/Ncmsc","l":"ב","lg":"in/H5612H=סֵ֫פֶר=: book"},{"n":9,"w":"תּוֹרַת","t":"to.Rat","g":"[the] law of","s":"H8451","m":"HNcfsc","l":"תּוֹרָה","lg":"instruction"},{"n":10,"w":"מֹשֶׁה","t":"mo.Sheh","g":"Moses","s":"H4872","m":"HNpm","l":"מֹשֶׁה","lg":"Moses"},{"n":11,"w":"לְ/בִלְתִּי","t":"le./vil.Ti","g":"to not","s":"H9005","m":"HR/Ncbsa","l":"ל","lg":"to/H1115=בִּלְתִּי=lest"},{"n":12,"w":"סוּר\\","t":"sur-","g":"to turn aside","s":"H5493I\\H9014","m":"HVqcc","l":"סוּר","lg":": turn_aside"},{"n":13,"w":"מִמֶּ/נּוּ","t":"mi.Me./nu","g":"from it","s":"H4480A","m":"HRd/Sp3ms","l":"מִן־","lg":"from/H9033=Os3m=him"},{"n":14,"w":"יָמִין","t":"ya.Min","g":"right [hand]","s":"H3225G","m":"HNcfsa","l":"יָמִין","lg":": right"},{"n":15,"w":"וּ/שְׂמֹאול\\","t":"u./se.Mol","g":"and left [hand]","s":"H9002","m":"HC/Ncmsa","l":"ו","lg":"and/H8040G=שְׂמֹאל=:left"}],"7":[{"n":1,"w":"לְ/בִלְתִּי\\","t":"le./vil.ti-","g":"to not","s":"H9005","m":"HR/Ncbsa","l":"ל","lg":"to/H1115=בִּלְתִּי=lest\\H9014=־=link"},{"n":2,"w":"בוֹא","t":"Vo'","g":"to go","s":"H0935G","m":"HVqcc","l":"בּוֹא","lg":": come"},{"n":3,"w":"בַּ/גּוֹיִם","t":"ba./go.Yim","g":"among the nations","s":"H9003","m":"HRd/Ncmpa","l":"ב","lg":"in/H1471A=גּוֹי=nation"},{"n":4,"w":"הָ/אֵלֶּה","t":"ha./'E.leh","g":"<the> these","s":"H9009","m":"HTd/Tm","l":"ה","lg":"the/H0428=אֵ֫לֶּה=these"},{"n":5,"w":"הַ/נִּשְׁאָרִים","t":"ha./nish.'a.Rim","g":"which remain","s":"H9009","m":"HTd/VNrmpa","l":"ה","lg":"the/H7604=שָׁאַר=to remain"},{"n":6,"w":"הָ/אֵלֶּה","t":"ha./'E.leh","g":"<the> these","s":"H9009","m":"HTd/Tm","l":"ה","lg":"the/H0428=אֵ֫לֶּה=these"},{"n":7,"w":"אִתְּ/כֶם","t":"'i.te./Khem","g":"with you","s":"H0854","m":"HRd/Sp2mp","l":"אֵת","lg":"with/H9036=Op2m=you"},{"n":8,"w":"וּ/בְ/שֵׁם","t":"u./ve./Shem","g":"and <in> [the] name of","s":"H9002","m":"HC/R/Ncmsc","l":"ו","lg":"and/H9003=ב=in/H8034=שֵׁם=name"},{"n":9,"w":"אֱלֹהֵי/הֶם","t":"'e.lo.hei./Hem","g":"gods their","s":"H0430J","m":"HNcmpc/Sp3mp","l":"אֱלֹהִים","lg":"gods/H9028=Pp3m=their"},{"n":10,"w":"לֹא\\","t":"lo'-","g":"not","s":"H3808\\H9014","m":"HTn","l":"לֹא","lg":"not\\H9014=־=link"},{"n":11,"w":"תַזְכִּירוּ","t":"taz.Ki.ru","g":"you must bring to remembrance","s":"H2142","m":"HVhi2mp","l":"זָכַר","lg":"to remember"},{"n":12,"w":"וְ/לֹא","t":"ve./Lo'","g":"and not","s":"H9002","m":"HC/Tn","l":"ו","lg":"and/H3808=לֹא=not"},{"n":13,"w":"תַשְׁבִּיעוּ","t":"tash.Bi.'u","g":"you must cause to swear","s":"H7650","m":"HVhi2mp","l":"שָׁבַע","lg":"to swear"},{"n":14,"w":"וְ/לֹא","t":"ve./Lo'","g":"and not","s":"H9002","m":"HC/Tn","l":"ו","lg":"and/H3808=לֹא=not"},{"n":15,"w":"תַעַבְדוּ/ם","t":"ta.'av.Du/m","g":"you must serve them","s":"H5647H","m":"HVqi2mp/Sp3mp","l":"עָבַד","lg":": minister"},{"n":16,"w":"וְ/לֹא","t":"ve./Lo'","g":"and not","s":"H9002","m":"HC/Tn","l":"ו","lg":"and/H3808=לֹא=not"},{"n":17,"w":"תִשְׁתַּחֲווּ","t":"tish.ta.cha.Vu","g":"you must bow down","s":"H7812","m":"HVti2mp","l":"שָׁחָה","lg":"to bow"},{"n":18,"w":"לָ/הֶם\\","t":"la./Hem","g":"to <the> them","s":"H9005","m":"HRd/Sp3mp","l":"ל","lg":"to/H9038=Op3m=them\\H9016=׃=verseEnd"}],"8":[{"n":1,"w":"כִּי","t":"ki","g":"that","s":"H3588B","m":"HTc","l":"כִּי","lg":""},{"n":2,"w":"אִם\\","t":"'im-","g":"except","s":"H0518B\\H9014","m":"HTc","l":"־","lg":"link"},{"n":3,"w":"בַּ/יהוָה","t":"ba./Yah.weh","g":"to Yahweh","s":"H9003","m":"HR/Npt","l":"ב","lg":"in/H3068G=יהוה=LORD"},{"n":4,"w":"אֱלֹהֵי/כֶם","t":"'e.lo.hei./Khem","g":"God your","s":"H0430G","m":"HNcmpc/Sp2mp","l":"אֱלֹהִים","lg":"God"},{"n":5,"w":"תִּדְבָּקוּ","t":"tid.Ba.ku","g":"you will cling","s":"H1692","m":"HVqi2mp","l":"דָּבַק","lg":"to cleave"},{"n":6,"w":"כַּ/אֲשֶׁר","t":"ka./'a.Sher","g":"just as","s":"H9004","m":"HR/Tr","l":"כ","lg":"like/H0834D=כַּאֲשֶׁר=as which"},{"n":7,"w":"עֲשִׂיתֶם","t":"'a.si.Tem","g":"you have done","s":"H6213A","m":"HVqp2mp","l":"עָשָׂה","lg":": do"},{"n":8,"w":"עַד","t":"'ad","g":"until","s":"H5704","m":"HR","l":"עַד","lg":"till"},{"n":9,"w":"הַ/יּוֹם","t":"hai./Yom","g":"the day","s":"H9009","m":"HTd/Ncmsa","l":"ה","lg":"the/H3117L=יוֹם=: today"},{"n":10,"w":"הַ/זֶּה\\","t":"ha./Zeh","g":"<the> this","s":"H9009","m":"HTd/Tm","l":"ה","lg":"the/H2088=זֶה=this\\H9016=׃=verseEnd"}],"9":[{"n":1,"w":"וַ/יּוֹרֶשׁ","t":"va/i.Yo.resh","g":"and he has dispossessed","s":"H9001","m":"Hc/Vhw3ms","l":"ו","lg":"&/H3423H=יָרַשׁ=: take"},{"n":2,"w":"יְהוָה","t":"Yah.weh","g":"Yahweh","s":"H3068G","m":"HNpt","l":"יהוה","lg":"LORD"},{"n":3,"w":"מִ/פְּנֵי/כֶם","t":"mi./pe.nei./Khem","g":"from before you","s":"H9006","m":"HR/Ncmpc/Sp2mp","l":"מ","lg":"from/H6440G=פָּנֶה=: before"},{"n":4,"w":"גּוֹיִם","t":"go.Yim","g":"nations","s":"H1471A","m":"HNcmpa","l":"גּוֹי","lg":"nation"},{"n":5,"w":"גְּדֹלִים","t":"ge.do.Lim","g":"great","s":"H1419A","m":"HAampa","l":"גַּל","lg":": large"},{"n":6,"w":"וַ/עֲצוּמִים","t":"va./'a.tzu.Mim","g":"and mighty","s":"H9002","m":"HC/Aampa","l":"ו","lg":"and/H6099=עָצוּם=mighty"},{"n":7,"w":"וְ/אַתֶּם","t":"ve./'a.Tem","g":"and you","s":"H9002","m":"HC/Pp2mp","l":"ו","lg":"and/H0859D=אַתֶּם=you(m.p.)"},{"n":8,"w":"לֹא\\","t":"lo'-","g":"not","s":"H3808\\H9014","m":"HTn","l":"לֹא","lg":"not\\H9014=־=link"},{"n":9,"w":"עָמַד","t":"'A.mad","g":"he has stood","s":"H5975G","m":"HVqp3ms","l":"עָמַד","lg":": stand"},{"n":10,"w":"אִישׁ","t":"'ish","g":"anyone","s":"H0376I","m":"HNcmsa","l":"אִישׁ","lg":": anyone"},{"n":11,"w":"בִּ/פְנֵי/כֶם","t":"bi/f.nei./Khem","g":"in faces your","s":"H9003","m":"HR/Ncmpc/Sp2mp","l":"ב","lg":"in/H6440G=פָּנֶה=: before"},{"n":12,"w":"עַד","t":"'ad","g":"until","s":"H5704","m":"HR","l":"עַד","lg":"till"},{"n":13,"w":"הַ/יּוֹם","t":"hai./Yom","g":"the day","s":"H9009","m":"HTd/Ncmsa","l":"ה","lg":"the/H3117L=יוֹם=: today"},{"n":14,"w":"הַ/זֶּה\\","t":"ha./Zeh","g":"<the> this","s":"H9009","m":"HTd/Tm","l":"ה","lg":"the/H2088=זֶה=this\\H9016=׃=verseEnd"}],"10":[{"n":1,"w":"אִישׁ\\","t":"'ish-","g":"a man","s":"H0376G\\H9014","m":"HNcmsa","l":"אִישׁ","lg":": man"},{"n":2,"w":"אֶחָד","t":"'e.Chad","g":"one","s":"H0259","m":"HAcfsa","l":"אֶחָד","lg":"one"},{"n":3,"w":"מִ/כֶּם","t":"mi./Kem","g":"of <the> you","s":"H9006","m":"HRd/Sp2mp","l":"מ","lg":"from/H9036=Op2m=you"},{"n":4,"w":"יִרְדָּף\\","t":"yir.dof-","g":"he puts to flight","s":"H7291\\H9014","m":"HVqi3ms","l":"רָדַף","lg":"to pursue\\H9014=־=link"},{"n":5,"w":"אָלֶף","t":"'A.lef","g":"a thousand","s":"H0505G","m":"HAcbsa","l":"אֶ֫לֶף","lg":": thousand"},{"n":6,"w":"כִּי\\","t":"ki","g":"for","s":"H3588A\\H9015","m":"HTc","l":"כִּי","lg":"for\\H9015=׀=separate"},{"n":7,"w":"יְהוָה","t":"Yah.weh","g":"Yahweh","s":"H3068G","m":"HNpt","l":"יהוה","lg":"LORD"},{"n":8,"w":"אֱלֹהֵי/כֶם","t":"'e.lo.hei./Khem","g":"God your","s":"H0430G","m":"HNcmpc/Sp2mp","l":"אֱלֹהִים","lg":"God"},{"n":9,"w":"הוּא","t":"hu'","g":"he","s":"H1931","m":"HPp3ms","l":"הוּא","lg":"he;_she;_it"},{"n":10,"w":"הַ/נִּלְחָם","t":"ha./nil.Cham","g":"[is] the [one who] fights","s":"H9009","m":"HTd/VNrmsa","l":"ה","lg":"the/H3898A=לָחַם=to fight"},{"n":11,"w":"לָ/כֶם","t":"la./Khem","g":"for <the> you","s":"H9005","m":"HRd/Sp2mp","l":"ל","lg":"to/H9036=Op2m=you"},{"n":12,"w":"כַּ/אֲשֶׁר","t":"ka./'a.Sher","g":"just as","s":"H9004","m":"HR/Tr","l":"כ","lg":"like/H0834D=כַּאֲשֶׁר=as which"},{"n":13,"w":"דִּבֶּר","t":"di.Ber","g":"he spoke","s":"H1696I","m":"HVpp3ms","l":"דָבַר","lg":": promise"},{"n":14,"w":"לָ/כֶם\\","t":"la./Khem","g":"to <the> you","s":"H9005","m":"HRd/Sp2mp","l":"ל","lg":"to/H9036=Op2m=you\\H9016=׃=verseEnd"}],"11":[{"n":1,"w":"וְ/נִשְׁמַרְתֶּם","t":"ve./nish.mar.Tem","g":"and you will take heed","s":"H9001","m":"Hc/VNq2mp","l":"ו","lg":"&/H8104J=שָׁמַר=: careful"},{"n":2,"w":"מְאֹד","t":"me.'Od","g":"exceedingly","s":"H3966","m":"HAcmsa","l":"מְאֹד","lg":"much"},{"n":3,"w":"לְ/נַפְשֹׁתֵי/כֶם","t":"le./naf.sho.tei./Khem","g":"to selves your","s":"H9005","m":"HR/Ncfpc/Sp2mp","l":"ל","lg":"to/H5315I=נֶ֫פֶשׁ=: myself"},{"n":4,"w":"לְ/אַהֲבָה","t":"le./'a.ha.Vah","g":"to love","s":"H9005","m":"HR/Vqcc","l":"ל","lg":"to/H0157G=אָהֵב=: lover"},{"n":5,"w":"אֶת\\","t":"'et-","g":"<obj.>","s":"H0853\\H9014","m":"HTo","l":"אֵת","lg":"[Obj.]\\H9014=־=link"},{"n":6,"w":"יְהוָה","t":"Yah.weh","g":"Yahweh","s":"H3068G","m":"HNpt","l":"יהוה","lg":"LORD"},{"n":7,"w":"אֱלֹהֵי/כֶם\\","t":"'e.lo.hei./Khem","g":"God your","s":"H0430G","m":"HNcmpc/Sp2mp","l":"אֱלֹהִים","lg":"God"}],"12":[{"n":1,"w":"כִּי\\","t":"ki","g":"that","s":"H3588A\\H9015","m":"HTc","l":"כִּי","lg":"for\\H9015=׀=separate"},{"n":2,"w":"אִם\\","t":"'im-","g":"except","s":"H0518B\\H9014","m":"HTc","l":"־","lg":"link"},{"n":3,"w":"שׁוֹב","t":"Shov","g":"ever <to turn back>","s":"H7725G","m":"HVqaa","l":"שׁוּב","lg":": return"},{"n":4,"w":"תָּשׁוּבוּ","t":"ta.Shu.vu","g":"you will turn back","s":"H7725G","m":"HVqi2mp","l":"שׁוּב","lg":": return"},{"n":5,"w":"וּ/דְבַקְתֶּם","t":"u./de.vak.Tem","g":"and you will cling","s":"H9001","m":"Hc/Vqq2mp","l":"ו","lg":"&/H1692=דָּבַק=to cleave"},{"n":6,"w":"בְּ/יֶתֶר","t":"be./Ye.ter","g":"to [the] remainder of","s":"H9003","m":"HR/Ncmsc","l":"ב","lg":"in/H3499A=יֶ֫תֶר=remainder"},{"n":7,"w":"הַ/גּוֹיִם","t":"ha./go.Yim","g":"the nations","s":"H9009","m":"HTd/Ncmpa","l":"ה","lg":"the/H1471A=גּוֹי=nation"},{"n":8,"w":"הָ/אֵלֶּה","t":"ha./'E.leh","g":"<the> these","s":"H9009","m":"HTd/Tm","l":"ה","lg":"the/H0428=אֵ֫לֶּה=these"},{"n":9,"w":"הַ/נִּשְׁאָרִים","t":"ha./nish.'a.Rim","g":"which remain","s":"H9009","m":"HTd/VNrmpa","l":"ה","lg":"the/H7604=שָׁאַר=to remain"},{"n":10,"w":"הָ/אֵלֶּה","t":"ha./'E.leh","g":"<the> these","s":"H9009","m":"HTd/Tm","l":"ה","lg":"the/H0428=אֵ֫לֶּה=these"},{"n":11,"w":"אִתְּ/כֶם","t":"'i.te./Khem","g":"with you","s":"H0854","m":"HRd/Sp2mp","l":"אֵת","lg":"with/H9036=Op2m=you"},{"n":12,"w":"וְ/הִתְחַתַּנְתֶּם","t":"ve./hit.cha.tan.Tem","g":"and you will intermarry","s":"H9001","m":"Hc/Vtq2mp","l":"ו","lg":"&/H2859B=חָתַן=be related"},{"n":13,"w":"בָּ/הֶם","t":"ba./Hem","g":"with <the> them","s":"H9003","m":"HRd/Sp3mp","l":"ב","lg":"in/H9038=Op3m=them"},{"n":14,"w":"וּ/בָאתֶם","t":"u./va.Tem","g":"and you will go","s":"H9001","m":"Hc/Vqq2mp","l":"ו","lg":"&/H0935L=בּוֹא=: marry"},{"n":15,"w":"בָּ/הֶם","t":"ba./Hem","g":"among <the> them","s":"H9003","m":"HRd/Sp3mp","l":"ב","lg":"in/H9038=Op3m=them"},{"n":16,"w":"וְ/הֵם","t":"ve./Hem","g":"and they","s":"H9002","m":"HC/Pp3mp","l":"ו","lg":"and/H1992=הֵ֫מָּה=they(masc.)"},{"n":17,"w":"בָּ/כֶם\\","t":"ba./Khem","g":"among <the> you","s":"H9003","m":"HRd/Sp2mp","l":"ב","lg":"in/H9036=Op2m=you\\H9016=׃=verseEnd"}],"13":[{"n":1,"w":"יָדוֹעַ","t":"ya.Do.a'","g":"certainly <to know>","s":"H3045","m":"HVqaa","l":"יָדַע","lg":"to know"},{"n":2,"w":"תֵּדְעוּ","t":"te.de.'U","g":"you will know","s":"H3045","m":"HVqi2mp","l":"יָדַע","lg":"to know"},{"n":3,"w":"כִּי","t":"ki","g":"that","s":"H3588A","m":"HTc","l":"כִּי","lg":"for"},{"n":4,"w":"לֹא","t":"lo'","g":"not","s":"H3808","m":"HTn","l":"לֹא","lg":"not"},{"n":5,"w":"יוֹסִיף","t":"yo.Sif","g":"he will increase","s":"H3254G","m":"HVhi3ms","l":"יָסַף","lg":": again"},{"n":6,"w":"יְהוָה","t":"Yah.weh","g":"Yahweh","s":"H3068G","m":"HNpt","l":"יהוה","lg":"LORD"},{"n":7,"w":"אֱלֹהֵי/כֶם","t":"'e.lo.hei./Khem","g":"God your","s":"H0430G","m":"HNcmpc/Sp2mp","l":"אֱלֹהִים","lg":"God"},{"n":8,"w":"לְ/הוֹרִישׁ","t":"le./ho.Rish","g":"to dispossess","s":"H9005","m":"HR/Vhcc","l":"ל","lg":"to/H3423H=יָרַשׁ=: take"},{"n":9,"w":"אֶת\\","t":"'et-","g":"<obj.>","s":"H0853\\H9014","m":"HTo","l":"אֵת","lg":"[Obj.]\\H9014=־=link"},{"n":10,"w":"הַ/גּוֹיִם","t":"ha./go.Yim","g":"the nations","s":"H9009","m":"HTd/Ncmpa","l":"ה","lg":"the/H1471A=גּוֹי=nation"},{"n":11,"w":"הָ/אֵלֶּה","t":"ha./'E.leh","g":"<the> these","s":"H9009","m":"HTd/Tm","l":"ה","lg":"the/H0428=אֵ֫לֶּה=these"},{"n":12,"w":"מִ/לִּ/פְנֵי/כֶם","t":"mi./li/f.nei./Khem","g":"from to before you","s":"H9006","m":"HR/R/Ncmpc/Sp2mp","l":"מ","lg":"from/H9005=ל=to/H6440G=פָּנֶה=: before"},{"n":13,"w":"וְ/הָיוּ","t":"ve./ha.Yu","g":"and they will become","s":"H9001","m":"Hc/Vqq3cp","l":"ו","lg":"&/H1961=הָיָה=to be"},{"n":14,"w":"לָ/כֶם","t":"la./Khem","g":"for <the> you","s":"H9005","m":"HRd/Sp2mp","l":"ל","lg":"to/H9036=Op2m=you"},{"n":15,"w":"לְ/פַח","t":"le./Fach","g":"<into> a trap","s":"H9005","m":"HR/Ncmsa","l":"ל","lg":"to/H6341A=פַּח=snare"},{"n":16,"w":"וּ/לְ/מוֹקֵשׁ","t":"u./le./mo.Kesh","g":"and <into> a snare","s":"H9002","m":"HC/R/Ncmsa","l":"ו","lg":"and/H9005=ל=to/H4170=מוֹקֵשׁ=snare"},{"n":17,"w":"וּ/לְ/שֹׁטֵט","t":"u./le./sho.Tet","g":"and <into> a scourge","s":"H9002","m":"HC/R/Ncmsa","l":"ו","lg":"and/H9005=ל=to/H7850=שֹׁטֵט=scourge"},{"n":18,"w":"בְּ/צִדֵּי/כֶם","t":"be./tzi.dei./Khem","g":"in sides your","s":"H9003","m":"HR/Ncmpc/Sp2mp","l":"ב","lg":"in/H6654=צַד=side/H9026=Pp2m=your"},{"n":19,"w":"וְ/לִ/צְנִנִים","t":"ve./li/tz.ni.Nim","g":"and <into> thorns","s":"H9002","m":"HC/R/Ncmpa","l":"ו","lg":"and/H9005=ל=to/H6796=צָנִין=thorn"},{"n":20,"w":"בְּ/עֵינֵי/כֶם","t":"be./'ei.nei./Khem","g":"in view your","s":"H9003","m":"HR/Ncfdc/Sp2mp","l":"ב","lg":"in/H5869A=עַ֫יִן=: eye"},{"n":21,"w":"עַד\\","t":"'ad-","g":"until","s":"H5704\\H9014","m":"HR","l":"עַד","lg":"till\\H9014=־=link"},{"n":22,"w":"אֲבָדְ/כֶם","t":"'a.va.de./Khem","g":"perish you","s":"H0006","m":"HVqcc/Sp2mp","l":"אָבַד","lg":"to perish/H9046=Sp2m=you"},{"n":23,"w":"מֵ/עַל","t":"Me./'al","g":"from on","s":"H9006","m":"HR/R","l":"מ","lg":"from/H5921A=עַל=upon"},{"n":24,"w":"הָ/אֲדָמָה","t":"ha./'a.da.Mah","g":"the land","s":"H9009","m":"HTd/Ncfsa","l":"ה","lg":"the/H0127G=אֲדָמָה=: soil"},{"n":25,"w":"הַ/טּוֹבָה","t":"ha./to.Vah","g":"<the> good","s":"H9009","m":"HTd/Aafsa","l":"ה","lg":"the/H2896A=טוֹב=pleasant"},{"n":26,"w":"הַ/זֹּאת","t":"ha./Zot","g":"<the> this","s":"H9009","m":"HTd/Tm","l":"ה","lg":"the/H2063=זֹאת=this"},{"n":27,"w":"אֲשֶׁר","t":"'a.Sher","g":"which","s":"H0834A","m":"HTr","l":"אֲשֶׁר","lg":"which"},{"n":28,"w":"נָתַן","t":"na.Tan","g":"he has given","s":"H5414G","m":"HVqp3ms","l":"נָתַן","lg":": give"},{"n":29,"w":"לָ/כֶם","t":"la./Khem","g":"to <the> you","s":"H9005","m":"HRd/Sp2mp","l":"ל","lg":"to/H9036=Op2m=you"},{"n":30,"w":"יְהוָה","t":"Yah.weh","g":"Yahweh","s":"H3068G","m":"HNpt","l":"יהוה","lg":"LORD"},{"n":31,"w":"אֱלֹהֵי/כֶם\\","t":"'e.lo.hei./Khem","g":"God your","s":"H0430G","m":"HNcmpc/Sp2mp","l":"אֱלֹהִים","lg":"God"}],"14":[{"n":1,"w":"וְ/הִנֵּה","t":"ve./hi.Neh","g":"and here!","s":"H9002","m":"HC/Tj","l":"ו","lg":"and/H2009=הִנֵּה=behold"},{"n":2,"w":"אָנֹכִי","t":"'a.no.Khi","g":"I","s":"H0595","m":"HPp1bs","l":"אָֽנֹכִ֫י","lg":"I"},{"n":3,"w":"הוֹלֵךְ","t":"ho.leKh","g":"[am] about to go","s":"H1980G","m":"HVqrmsa","l":"הָלַךְ","lg":": went"},{"n":4,"w":"הַ/יּוֹם","t":"hai./Yom","g":"this day","s":"H9009","m":"HTd/Ncmsa","l":"ה","lg":"the/H3117L=יוֹם=: today"},{"n":5,"w":"בְּ/דֶרֶךְ","t":"be./De.rekh","g":"in [the] way of","s":"H9003","m":"HR/Ncbsc","l":"ב","lg":"in/H1870L=דֶּ֫רֶךְ=: journey"},{"n":6,"w":"כָּל\\","t":"kol-","g":"all","s":"H3605\\H9014","m":"HNcmsc","l":"כֹּל","lg":"all\\H9014=־=link"},{"n":7,"w":"הָ/אָרֶץ","t":"ha./'A.retz","g":"the earth","s":"H9009","m":"HTd/Ncfsa","l":"ה","lg":"the/H0776G=אֶ֫רֶץ=: country;_planet"},{"n":8,"w":"וִ/ידַעְתֶּם","t":"vi./da'.Tem","g":"and you know","s":"H9001","m":"Hc/Vqq2mp","l":"ו","lg":"&/H3045=יָדַע=to know"},{"n":9,"w":"בְּ/כָל\\","t":"be./khol","g":"with all","s":"H9003","m":"HR/Ncmsc","l":"ב","lg":"in/H3605=כֹּל=all\\H9014=־=link"},{"n":10,"w":"לְבַבְ/כֶם","t":"le.vav./Khem","g":"heart your","s":"H3824","m":"HNcmsc/Sp2mp","l":"לֵבָב","lg":"heart/H9026=Pp2m=your"},{"n":11,"w":"וּ/בְ/כָל\\","t":"u./ve./Khol-","g":"and with all","s":"H9002","m":"HC/R/Ncmsc","l":"ו","lg":"and/H9003=ב=in/H3605=כֹּל=all\\H9014=־=link"},{"n":12,"w":"נַפְשְׁ/כֶם","t":"naf.she./Khem","g":"being your","s":"H5315G","m":"HNcfsc/Sp2mp","l":"נֶ֫פֶשׁ","lg":": soul"},{"n":13,"w":"כִּי","t":"ki","g":"that","s":"H3588A","m":"HTc","l":"כִּי","lg":"for"},{"n":14,"w":"לֹא\\","t":"lo'-","g":"not","s":"H3808\\H9014","m":"HTn","l":"לֹא","lg":"not\\H9014=־=link"},{"n":15,"w":"נָפַל","t":"na.Fal","g":"it has fallen","s":"H5307L","m":"HVqp3ms","l":"נָפַל","lg":": fail"},{"n":16,"w":"דָּבָר","t":"da.Var","g":"a word","s":"H1697I","m":"HNcmsa","l":"דָּבָר","lg":": thing"},{"n":17,"w":"אֶחָד","t":"'e.Chad","g":"one","s":"H0259","m":"HAcfsa","l":"אֶחָד","lg":"one"},{"n":18,"w":"מִ/כֹּל\\","t":"mi./Kol","g":"of all","s":"H9006","m":"HR/Ncmsc","l":"מ","lg":"from/H3605=כֹּל=all\\H9015=׀=separate"},{"n":19,"w":"הַ/דְּבָרִים","t":"ha./de.va.Rim","g":"the words","s":"H9009","m":"HTd/Ncmpa","l":"ה","lg":"the/H1697I=דָּבָר=: thing"},{"n":20,"w":"הַ/טּוֹבִים","t":"ha./to.Vim","g":"<the> good","s":"H9009","m":"HTd/Aampa","l":"ה","lg":"the/H2896A=טוֹב=pleasant"},{"n":21,"w":"אֲשֶׁר","t":"'a.Sher","g":"which","s":"H0834A","m":"HTr","l":"אֲשֶׁר","lg":"which"},{"n":22,"w":"דִּבֶּר","t":"di.Ber","g":"he spoke","s":"H1696I","m":"HVpp3ms","l":"דָבַר","lg":": promise"},{"n":23,"w":"יְהוָה","t":"Yah.weh","g":"Yahweh","s":"H3068G","m":"HNpt","l":"יהוה","lg":"LORD"},{"n":24,"w":"אֱלֹהֵי/כֶם","t":"'e.lo.hei./Khem","g":"God your","s":"H0430G","m":"HNcmpc/Sp2mp","l":"אֱלֹהִים","lg":"God"},{"n":25,"w":"עֲלֵי/כֶם","t":"'a.lei./Khem","g":"on you","s":"H5921A","m":"HRd/Sp2mp","l":"עַל","lg":"upon/H9036=Op2m=you"},{"n":26,"w":"הַ/כֹּל","t":"ha./Kol","g":"<the> everything","s":"H9009","m":"HTd/Ncmsa","l":"ה","lg":"the/H3605=כֹּל=all"},{"n":27,"w":"בָּאוּ","t":"Ba.'u","g":"they have come","s":"H0935G","m":"HVqp3cp","l":"בּוֹא","lg":": come"},{"n":28,"w":"לָ/כֶם","t":"la./Khem","g":"to <the> you","s":"H9005","m":"HRd/Sp2mp","l":"ל","lg":"to/H9036=Op2m=you"},{"n":29,"w":"לֹא\\","t":"lo'-","g":"not","s":"H3808\\H9014","m":"HTn","l":"לֹא","lg":"not\\H9014=־=link"},{"n":30,"w":"נָפַל","t":"na.Fal","g":"it has fallen","s":"H5307L","m":"HVqp3ms","l":"נָפַל","lg":": fail"},{"n":31,"w":"מִמֶּ/נּוּ","t":"mi.Me./nu","g":"of it","s":"H4480A","m":"HRd/Sp3ms","l":"מִן־","lg":"from/H9033=Os3m=him"},{"n":32,"w":"דָּבָר","t":"da.Var","g":"a word","s":"H1697I","m":"HNcmsa","l":"דָּבָר","lg":": thing"},{"n":33,"w":"אֶחָד\\","t":"'e.Chad","g":"one","s":"H0259\\H9016","m":"HAcfsa","l":"אֶחָד","lg":"one\\H9016=׃=verseEnd"}],"15":[{"n":1,"w":"וְ/הָיָה","t":"ve./ha.Yah","g":"and it will be","s":"H9001","m":"Hc/Vqq3ms","l":"ו","lg":"&/H1961=הָיָה=to be"},{"n":2,"w":"כַּ/אֲשֶׁר\\","t":"ka./'a.Sher-","g":"just as","s":"H9004","m":"HR/Tr","l":"כ","lg":"like/H0834D=כַּאֲשֶׁר=as which\\H9014=־=link"},{"n":3,"w":"בָּא","t":"ba'","g":"it has come","s":"H0935M","m":"HVqp3ms","l":"בּוֹא","lg":": fulfill"},{"n":4,"w":"עֲלֵי/כֶם","t":"'a.lei./Khem","g":"on you","s":"H5921A","m":"HRd/Sp2mp","l":"עַל","lg":"upon/H9036=Op2m=you"},{"n":5,"w":"כָּל\\","t":"kol-","g":"every","s":"H3605\\H9014","m":"HNcmsc","l":"כֹּל","lg":"all\\H9014=־=link"},{"n":6,"w":"הַ/דָּבָר","t":"ha./da.Var","g":"<the> word","s":"H9009","m":"HTd/Ncmsa","l":"ה","lg":"the/H1697I=דָּבָר=: thing"},{"n":7,"w":"הַ/טּוֹב","t":"ha./Tov","g":"<the> good","s":"H9009","m":"HTd/Aamsa","l":"ה","lg":"the/H2896A=טוֹב=pleasant"},{"n":8,"w":"אֲשֶׁר","t":"'a.Sher","g":"which","s":"H0834A","m":"HTr","l":"אֲשֶׁר","lg":"which"},{"n":9,"w":"דִּבֶּר","t":"di.Ber","g":"he spoke","s":"H1696I","m":"HVpp3ms","l":"דָבַר","lg":": promise"},{"n":10,"w":"יְהוָה","t":"Yah.weh","g":"Yahweh","s":"H3068G","m":"HNpt","l":"יהוה","lg":"LORD"},{"n":11,"w":"אֱלֹהֵי/כֶם","t":"'e.lo.hei./Khem","g":"God your","s":"H0430G","m":"HNcmpc/Sp2mp","l":"אֱלֹהִים","lg":"God"},{"n":12,"w":"אֲלֵי/כֶם","t":"'a.lei./Khem","g":"to you","s":"H0413","m":"HRd/Sp2mp","l":"אֶל","lg":"to(wards)/H9036=Op2m=you"},{"n":13,"w":"כֵּן","t":"ken","g":"so","s":"H3651C","m":"HD","l":"כֵּן","lg":"so"},{"n":14,"w":"יָבִיא","t":"ya.Vi'","g":"he will bring","s":"H0935P","m":"HVhi3ms","l":"בּוֹא","lg":": bring"},{"n":15,"w":"יְהוָה","t":"Yah.weh","g":"Yahweh","s":"H3068G","m":"HNpt","l":"יהוה","lg":"LORD"},{"n":16,"w":"עֲלֵי/כֶם","t":"'a.lei./Khem","g":"on you","s":"H5921A","m":"HRd/Sp2mp","l":"עַל","lg":"upon/H9036=Op2m=you"},{"n":17,"w":"אֵת","t":"'et","g":"<obj.>","s":"H0853","m":"HTo","l":"אֵת","lg":"[Obj.]"},{"n":18,"w":"כָּל\\","t":"kol-","g":"every","s":"H3605\\H9014","m":"HNcmsc","l":"כֹּל","lg":"all\\H9014=־=link"},{"n":19,"w":"הַ/דָּבָר","t":"ha./da.Var","g":"<the> word","s":"H9009","m":"HTd/Ncmsa","l":"ה","lg":"the/H1697I=דָּבָר=: thing"},{"n":20,"w":"הָ/רָע","t":"ha./Ra'","g":"<the> bad","s":"H9009","m":"HTd/Aamsa","l":"ה","lg":"the/H7451H=רַע=: evil"},{"n":21,"w":"עַד\\","t":"'ad-","g":"until","s":"H5704\\H9014","m":"HR","l":"עַד","lg":"till\\H9014=־=link"},{"n":22,"w":"הַשְׁמִיד/וֹ","t":"hash.mi.D/o","g":"has destroyed he","s":"H8045","m":"HVhcc/Sp3ms","l":"שָׁמַד","lg":"to destroy/H9043=Ss3m=he"},{"n":23,"w":"אוֹתְ/כֶם","t":"'ot./Khem","g":"<obj.> you","s":"H0853","m":"HTo/Sp2mp","l":"אֵת","lg":"[Obj.]/H9036=Op2m=you"},{"n":24,"w":"מֵ/עַל","t":"Me./'al","g":"from on","s":"H9006","m":"HR/R","l":"מ","lg":"from/H5921A=עַל=upon"},{"n":25,"w":"הָ/אֲדָמָה","t":"ha./'a.da.Mah","g":"the land","s":"H9009","m":"HTd/Ncfsa","l":"ה","lg":"the/H0127G=אֲדָמָה=: soil"},{"n":26,"w":"הַ/טּוֹבָה","t":"ha./to.Vah","g":"<the> good","s":"H9009","m":"HTd/Aafsa","l":"ה","lg":"the/H2896A=טוֹב=pleasant"},{"n":27,"w":"הַ/זֹּאת","t":"ha./Zot","g":"<the> this","s":"H9009","m":"HTd/Tm","l":"ה","lg":"the/H2063=זֹאת=this"},{"n":28,"w":"אֲשֶׁר","t":"'a.Sher","g":"which","s":"H0834A","m":"HTr","l":"אֲשֶׁר","lg":"which"},{"n":29,"w":"נָתַן","t":"na.Tan","g":"he has given","s":"H5414G","m":"HVqp3ms","l":"נָתַן","lg":": give"},{"n":30,"w":"לָ/כֶם","t":"la./Khem","g":"to <the> you","s":"H9005","m":"HRd/Sp2mp","l":"ל","lg":"to/H9036=Op2m=you"},{"n":31,"w":"יְהוָה","t":"Yah.weh","g":"Yahweh","s":"H3068G","m":"HNpt","l":"יהוה","lg":"LORD"},{"n":32,"w":"אֱלֹהֵי/כֶם\\","t":"'e.lo.hei./Khem","g":"God your","s":"H0430G","m":"HNcmpc/Sp2mp","l":"אֱלֹהִים","lg":"God"}],"16":[{"n":1,"w":"בְּ/עָבְרְ/כֶם","t":"Be./'a.ve.re./khem","g":"when transgress you","s":"H9003","m":"HR/Vqcc/Sp2mp","l":"ב","lg":"in/H5674D=עָבַר=: trespass"},{"n":2,"w":"אֶת\\","t":"'et-","g":"<obj.>","s":"H0853\\H9014","m":"HTo","l":"אֵת","lg":"[Obj.]\\H9014=־=link"},{"n":3,"w":"בְּרִית","t":"be.Rit","g":"[the] covenant of","s":"H1285","m":"HNcfsc","l":"בְּרִית","lg":"covenant"},{"n":4,"w":"יְהוָה","t":"Yah.weh","g":"Yahweh","s":"H3068G","m":"HNpt","l":"יהוה","lg":"LORD"},{"n":5,"w":"אֱלֹהֵי/כֶם","t":"'e.lo.hei./Khem","g":"God your","s":"H0430G","m":"HNcmpc/Sp2mp","l":"אֱלֹהִים","lg":"God"},{"n":6,"w":"אֲשֶׁר","t":"'a.Sher","g":"which","s":"H0834A","m":"HTr","l":"אֲשֶׁר","lg":"which"},{"n":7,"w":"צִוָּה","t":"tzi.Vah","g":"he commanded","s":"H6680","m":"HVpp3ms","l":"צָוָה","lg":"to command"},{"n":8,"w":"אֶתְ/כֶם","t":"'et./Khem","g":"<obj.> you","s":"H0853","m":"HTo/Sp2mp","l":"אֵת","lg":"[Obj.]/H9036=Op2m=you"},{"n":9,"w":"וַ/הֲלַכְתֶּם","t":"va./ha.lakh.Tem","g":"and you will go","s":"H9001","m":"Hc/Vqq2mp","l":"ו","lg":"&/H1980G=הָלַךְ=: went"},{"n":10,"w":"וַ/עֲבַדְתֶּם","t":"va./'a.vad.Tem","g":"and you will serve","s":"H9001","m":"Hc/Vqq2mp","l":"ו","lg":"&/H5647H=עָבַד=: minister"},{"n":11,"w":"אֱלֹהִים","t":"'E.lo.Him","g":"gods","s":"H0430J","m":"HNcmpa","l":"אֱלֹהִים","lg":"gods"},{"n":12,"w":"אֲחֵרִים","t":"'a.che.Rim","g":"other","s":"H0312","m":"HAampa","l":"אַחֵר","lg":"another"},{"n":13,"w":"וְ/הִשְׁתַּחֲוִיתֶם","t":"ve./hish.ta.cha.vi.Tem","g":"and you will bow down","s":"H9001","m":"Hc/Vvq2mp","l":"ו","lg":"&/H7812=שָׁחָה=to bow"},{"n":14,"w":"לָ/הֶם","t":"la./Hem","g":"to <the> them","s":"H9005","m":"HRd/Sp3mp","l":"ל","lg":"to/H9038=Op3m=them"},{"n":15,"w":"וְ/חָרָה","t":"ve./cha.Rah","g":"and it will burn","s":"H9001","m":"Hc/Vqq3ms","l":"ו","lg":"&/H2734=חָרָה=to burn"},{"n":16,"w":"אַף\\","t":"'af-","g":"[the] anger of","s":"H0639G\\H9014","m":"HNcmsc","l":"אַף","lg":": anger"},{"n":17,"w":"יְהוָה","t":"Yah.weh","g":"Yahweh","s":"H3068G","m":"HNpt","l":"יהוה","lg":"LORD"},{"n":18,"w":"בָּ/כֶם","t":"ba./Khem","g":"on <the> you","s":"H9003","m":"HRd/Sp2mp","l":"ב","lg":"in/H9036=Op2m=you"},{"n":19,"w":"וַ/אֲבַדְתֶּם","t":"va./'a.vad.Tem","g":"and you will perish","s":"H9001","m":"Hc/Vqq2mp","l":"ו","lg":"&/H0006=אָבַד=to perish"},{"n":20,"w":"מְהֵרָה","t":"me.he.Rah","g":"quickly","s":"H4120","m":"HD","l":"מְהֵרָה","lg":"haste"},{"n":21,"w":"מֵ/עַל","t":"me./'Al","g":"from on","s":"H9006","m":"HR/R","l":"מ","lg":"from/H5921A=עַל=upon"},{"n":22,"w":"הָ/אָרֶץ","t":"ha./'A.retz","g":"the land","s":"H9009","m":"HTd/Ncfsa","l":"ה","lg":"the/H0776G=אֶ֫רֶץ=: country;_planet"},{"n":23,"w":"הַ/טּוֹבָה","t":"ha./to.Vah","g":"<the> good","s":"H9009","m":"HTd/Aafsa","l":"ה","lg":"the/H2896A=טוֹב=pleasant"},{"n":24,"w":"אֲשֶׁר","t":"'a.Sher","g":"which","s":"H0834A","m":"HTr","l":"אֲשֶׁר","lg":"which"},{"n":25,"w":"נָתַן","t":"na.Tan","g":"he has given","s":"H5414G","m":"HVqp3ms","l":"נָתַן","lg":": give"},{"n":26,"w":"לָ/כֶם\\\\ \\פ","t":"la./Khem","g":"to <the> you","s":"H9005","m":"HRd/Sp2mp","l":"ל","lg":"to/H9036=Op2m=you\\H9016=׃=verseEnd\\ \\H9017=פ=para"}]}