{"1":[{"n":1,"w":"Ὀφείλομεν","t":"Opheilomen","g":"We ought","s":"G3784","m":"V-PAI-1P","l":"ὀφείλω","lg":"to owe"},{"n":2,"w":"δὲ","t":"de","g":"now","s":"G1161","m":"CONJ","l":"δέ","lg":"but/and"},{"n":3,"w":"ἡμεῖς","t":"hēmeis","g":"we ourselves","s":"G3165","m":"P-1NP","l":"ἐγώ","lg":"I/we"},{"n":4,"w":"οἱ","t":"hoi","g":"who [are]","s":"G3588","m":"T-NPM","l":"ὁ","lg":"the/this/who"},{"n":5,"w":"δυνατοὶ","t":"dunatoi","g":"strong","s":"G1415","m":"A-NPM","l":"δυνατός","lg":"able"},{"n":6,"w":"τὰ","t":"ta","g":"the","s":"G3588","m":"T-APN","l":"ὁ","lg":"the/this/who"},{"n":7,"w":"ἀσθενήματα","t":"asthenēmata","g":"weaknesses","s":"G0771","m":"N-APN","l":"ἀσθένημα","lg":"weakness"},{"n":8,"w":"τῶν","t":"tōn","g":"of the","s":"G3588","m":"T-GPM","l":"ὁ","lg":"the/this/who"},{"n":9,"w":"ἀδυνάτων","t":"adunatōn","g":"weak","s":"G0102","m":"A-GPM","l":"ἀδύνατος","lg":"unable"},{"n":10,"w":"βαστάζειν","t":"bastazein","g":"to bear","s":"G0941","m":"V-PAN","l":"βαστάζω","lg":"to carry"},{"n":11,"w":"καὶ","t":"kai","g":"and","s":"G2532","m":"CONJ","l":"καί","lg":"and"},{"n":12,"w":"μὴ","t":"mē","g":"not","s":"G3361","m":"PRT-N","l":"μή","lg":"not"},{"n":13,"w":"ἑαυτοῖς","t":"he'autois","g":"ourselves","s":"G1438","m":"F-1DPM","l":"ἑαυτοῦ","lg":"my/your/him-self"},{"n":14,"w":"ἀρέσκειν·","t":"areskein","g":"to please;","s":"G0700","m":"V-PAN","l":"ἀρέσκω","lg":"to please"}],"2":[{"n":1,"w":"ἕκαστος","t":"hekastos","g":"Each","s":"G1538","m":"A-NSM","l":"ἕκαστος","lg":"each"},{"n":2,"w":"γάρ","t":"gar","g":"for","s":"G1063","m":"CONJ","l":"γάρ","lg":"for"},{"n":3,"w":"ἡμῶν","t":"hēmōn","g":"of us","s":"G3165","m":"P-1GP","l":"ἐγώ","lg":"I/we"},{"n":4,"w":"τῷ","t":"tō","g":"the","s":"G3588","m":"T-DSM","l":"ὁ","lg":"the/this/who"},{"n":5,"w":"πλησίον","t":"plēsion","g":"neighbour","s":"G4139","m":"ADV","l":"πλησίον","lg":"near/neighbour"},{"n":6,"w":"ἀρεσκέτω","t":"aresketō","g":"should please","s":"G0700","m":"V-PAM-3S","l":"ἀρέσκω","lg":"to please"},{"n":7,"w":"εἰς","t":"eis","g":"unto","s":"G1519","m":"PREP","l":"εἰς","lg":"toward"},{"n":8,"w":"τὸ","t":"to","g":"the","s":"G3588","m":"T-ASN","l":"ὁ","lg":"the/this/who"},{"n":9,"w":"ἀγαθὸν","t":"agathon","g":"good","s":"G0018","m":"A-ASN","l":"ἀγαθός","lg":"good-doer"},{"n":10,"w":"πρὸς","t":"pros","g":"for","s":"G4314","m":"PREP","l":"πρός","lg":"to/with"},{"n":11,"w":"οἰκοδομήν.","t":"oikodomēn","g":"edification.","s":"G3619","m":"N-ASF","l":"οἰκοδομή","lg":"building"}],"3":[{"n":1,"w":"καὶ","t":"kai","g":"Even","s":"G2532","m":"CONJ","l":"καί","lg":"and"},{"n":2,"w":"γὰρ","t":"gar","g":"for","s":"G1063","m":"CONJ","l":"γάρ","lg":"for"},{"n":3,"w":"ὁ","t":"ho","g":"<the>","s":"G3588","m":"T-NSM","l":"ὁ","lg":"the/this/who"},{"n":4,"w":"Χριστὸς","t":"Christos","g":"Christ","s":"G5547","m":"N-NSM-T","l":"Χριστός","lg":"Christ"},{"n":5,"w":"οὐχ","t":"ouch","g":"not","s":"G3756","m":"PRT-N","l":"οὐ","lg":"no"},{"n":6,"w":"ἑαυτῷ","t":"he'autō","g":"Himself","s":"G1438","m":"F-3DSM","l":"ἑαυτοῦ","lg":"my/your/him-self"},{"n":7,"w":"ἤρεσεν","t":"ēresen","g":"pleased","s":"G0700","m":"V-AAI-3S","l":"ἀρέσκω","lg":"to please"},{"n":8,"w":"ἀλλὰ","t":"alla","g":"but","s":"G0235","m":"CONJ","l":"ἀλλά","lg":"but"},{"n":9,"w":"καθὼς","t":"kathōs","g":"even as","s":"G2531","m":"CONJ","l":"καθώς","lg":"as/just as"},{"n":10,"w":"γέγραπται·","t":"gegraptai","g":"it has been written:","s":"G1125","m":"V-RPI-3S","l":"γράφω","lg":"to write"},{"n":11,"w":"οἱ","t":"hoi","g":"The","s":"G3588","m":"T-NPM","l":"ὁ","lg":"the/this/who"},{"n":12,"w":"ὀνειδισμοὶ","t":"oneidismoi","g":"reproaches","s":"G3680","m":"N-NPM","l":"ὀνειδισμός","lg":"reproach"},{"n":13,"w":"τῶν","t":"tōn","g":"of those","s":"G3588","m":"T-GPM","l":"ὁ","lg":"the/this/who"},{"n":14,"w":"ὀνειδιζόντων","t":"oneidizontōn","g":"reproaching","s":"G3679","m":"V-PAP-GPM","l":"ὀνειδίζω","lg":"to revile"},{"n":15,"w":"σε","t":"se","g":"You","s":"G4771","m":"P-2AS","l":"σύ","lg":"you"},{"n":16,"w":"ἐπέπεσαν","t":"epepesan","g":"fell","s":"G1968","m":"V-AAI-3P","l":"ἐπιπίπτω","lg":"to fall/press upon"},{"n":17,"w":"ἐπ᾽","t":"ep᾽","g":"on","s":"G1909","m":"PREP","l":"ἐπί","lg":"upon/to/against"},{"n":18,"w":"ἐμέ.","t":"eme","g":"Me myself.","s":"G1473","m":"P-1AS","l":"ἐγώ","lg":"I/we"}],"4":[{"n":1,"w":"ὅσα","t":"hosa","g":"As much as","s":"G3745","m":"K-NPN","l":"ὅσος","lg":"just as/how much"},{"n":2,"w":"γὰρ","t":"gar","g":"for","s":"G1063","m":"CONJ","l":"γάρ","lg":"for"},{"n":3,"w":"προεγράφη","t":"proegraphē","g":"was written in the past","s":"G4270","m":"V-2API-3S","l":"προγράφω","lg":"to write/designate"},{"n":4,"w":"πάντα","t":"panta","g":"all things","s":"G3956","m":"A-NPN","l":"πᾶς","lg":"all"},{"n":5,"w":"εἰς","t":"eis","g":"for","s":"G1519","m":"PREP","l":"εἰς","lg":"toward"},{"n":6,"w":"τὴν","t":"tēn","g":"<the>","s":"G3588","m":"T-ASF","l":"ὁ","lg":"the/this/who"},{"n":7,"w":"ἡμετέραν","t":"hēmeteran","g":"our own","s":"G1473","m":"S-1PASF","l":"ἡμέτερος","lg":"our"},{"n":8,"w":"διδασκαλίαν","t":"didaskalian","g":"instruction","s":"G1319","m":"N-ASF","l":"διδασκαλία","lg":"teaching"},{"n":9,"w":"ἐγράφη,","t":"egraphē","g":"was written,","s":"G1125","m":"V-2API-3S","l":"γράφω","lg":"to write"},{"n":10,"w":"ἵνα","t":"ina","g":"so that","s":"G2443","m":"CONJ","l":"ἵνα","lg":"in order that/to"},{"n":11,"w":"διὰ","t":"dia","g":"through","s":"G1223","m":"PREP","l":"διά","lg":"through/because of"},{"n":12,"w":"τῆς","t":"tēs","g":"<the>","s":"G3588","m":"T-GSF","l":"ὁ","lg":"the/this/who"},{"n":13,"w":"ὑπομονῆς","t":"hupomonēs","g":"endurance","s":"G5281","m":"N-GSF","l":"ὑπομονή","lg":"perseverance"},{"n":14,"w":"καὶ","t":"kai","g":"and","s":"G2532","m":"CONJ","l":"καί","lg":"and"},{"n":15,"w":"διὰ","t":"dia","g":"through","s":"G1223","m":"PREP","l":"διά","lg":"through/because of"},{"n":16,"w":"τῆς","t":"tēs","g":"the","s":"G3588","m":"T-GSF","l":"ὁ","lg":"the/this/who"},{"n":17,"w":"παρακλήσεως","t":"paraklēseōs","g":"encouragement","s":"G3874","m":"N-GSF","l":"παράκλησις","lg":"encouragement"},{"n":18,"w":"τῶν","t":"tōn","g":"of the","s":"G3588","m":"T-GPF","l":"ὁ","lg":"the/this/who"},{"n":19,"w":"γραφῶν","t":"graphōn","g":"Scriptures","s":"G1124","m":"N-GPF","l":"γραφή","lg":"a writing"},{"n":20,"w":"τὴν","t":"tēn","g":"<the>","s":"G3588","m":"T-ASF","l":"ὁ","lg":"the/this/who"},{"n":21,"w":"ἐλπίδα","t":"elpida","g":"hope","s":"G1680","m":"N-ASF","l":"ἐλπίς","lg":"hope"},{"n":22,"w":"ἔχωμεν.¶","t":"echōmen","g":"we may have.","s":"G2192","m":"V-PAS-1P","l":"ἔχω","lg":"to have/be"}],"5":[{"n":1,"w":"Ὁ","t":"Ho","g":"The","s":"G3588","m":"T-NSM","l":"ὁ","lg":"the/this/who"},{"n":2,"w":"δὲ","t":"de","g":"now","s":"G1161","m":"CONJ","l":"δέ","lg":"but/and"},{"n":3,"w":"θεὸς","t":"theos","g":"God","s":"G2316","m":"N-NSM-T","l":"θεός","lg":"God"},{"n":4,"w":"τῆς","t":"tēs","g":"<the>","s":"G3588","m":"T-GSF","l":"ὁ","lg":"the/this/who"},{"n":5,"w":"ὑπομονῆς","t":"hupomonēs","g":"of endurance","s":"G5281","m":"N-GSF","l":"ὑπομονή","lg":"perseverance"},{"n":6,"w":"καὶ","t":"kai","g":"and","s":"G2532","m":"CONJ","l":"καί","lg":"and"},{"n":7,"w":"τῆς","t":"tēs","g":"<the>","s":"G3588","m":"T-GSF","l":"ὁ","lg":"the/this/who"},{"n":8,"w":"παρακλήσεως","t":"paraklēseōs","g":"encouragement","s":"G3874","m":"N-GSF","l":"παράκλησις","lg":"encouragement"},{"n":9,"w":"δῴη","t":"dōē","g":"would He give","s":"G1325","m":"V-2AAO-3S","l":"δίδωμι","lg":"to give"},{"n":10,"w":"ὑμῖν","t":"humin","g":"you","s":"G4771","m":"P-2DP","l":"σύ","lg":"you"},{"n":11,"w":"τὸ","t":"to","g":"the","s":"G3588","m":"T-ASN","l":"ὁ","lg":"the/this/who"},{"n":12,"w":"αὐτὸ","t":"auto","g":"same","s":"G0846","m":"P-ASN","l":"αὐτός","lg":"he/she/it/self"},{"n":13,"w":"φρονεῖν","t":"phronein","g":"to be of mind","s":"G5426","m":"V-PAN","l":"φρονέω","lg":"to reason"},{"n":14,"w":"ἐν","t":"en","g":"with","s":"G1722","m":"PREP","l":"ἐν","lg":"in/on/among"},{"n":15,"w":"ἀλλήλοις","t":"allēlois","g":"one another","s":"G0240","m":"C-DPM","l":"ἀλλήλων","lg":"one another"},{"n":16,"w":"κατὰ","t":"kata","g":"according to","s":"G2596","m":"PREP","l":"κατά","lg":"according to"},{"n":17,"w":"Χριστὸν","t":"Christon","g":"Christ","s":"G5547","m":"N-ASM-T","l":"Χριστός","lg":"Christ"},{"n":18,"w":"Ἰησοῦν","t":"Iēsoun","g":"Jesus","s":"G2424G","m":"N-ASM-P","l":"Ἰησοῦς","lg":"Jesus/Joshua"}],"6":[{"n":1,"w":"ἵνα","t":"ina","g":"so that","s":"G2443","m":"CONJ","l":"ἵνα","lg":"in order that/to"},{"n":2,"w":"ὁμοθυμαδὸν","t":"homothumadon","g":"with one accord","s":"G3661","m":"ADV","l":"ὁμοθυμαδόν","lg":"united"},{"n":3,"w":"ἐν","t":"en","g":"with","s":"G1722","m":"PREP","l":"ἐν","lg":"in/on/among"},{"n":4,"w":"ἑνὶ","t":"heni","g":"one","s":"G1520","m":"A-DSN","l":"εἷς","lg":"one"},{"n":5,"w":"στόματι","t":"stomati","g":"mouth","s":"G4750","m":"N-DSN","l":"στόμα","lg":"mouth"},{"n":6,"w":"δοξάζητε","t":"doxazēte","g":"you may glorify","s":"G1392","m":"V-PAS-2P","l":"δοξάζω","lg":"to glorify"},{"n":7,"w":"τὸν","t":"ton","g":"the","s":"G3588","m":"T-ASM","l":"ὁ","lg":"the/this/who"},{"n":8,"w":"θεὸν","t":"theon","g":"God","s":"G2316","m":"N-ASM-T","l":"θεός","lg":"God"},{"n":9,"w":"καὶ","t":"kai","g":"and","s":"G2532","m":"CONJ","l":"καί","lg":"and"},{"n":10,"w":"πατέρα","t":"patera","g":"Father","s":"G3962","m":"N-ASM-T","l":"πατήρ","lg":"father"},{"n":11,"w":"τοῦ","t":"tou","g":"of the","s":"G3588","m":"T-GSM","l":"ὁ","lg":"the/this/who"},{"n":12,"w":"κυρίου","t":"kuriou","g":"Lord","s":"G2962G","m":"N-GSM-T","l":"κύριος","lg":"lord"},{"n":13,"w":"ἡμῶν","t":"hēmōn","g":"of us","s":"G3165","m":"P-1GP","l":"ἐγώ","lg":"I/we"},{"n":14,"w":"Ἰησοῦ","t":"Iēsou","g":"Jesus","s":"G2424G","m":"N-GSM-P","l":"Ἰησοῦς","lg":"Jesus/Joshua"},{"n":15,"w":"Χριστοῦ.","t":"Christou","g":"Christ.","s":"G5547","m":"N-GSM-T","l":"Χριστός","lg":"Christ"}],"7":[{"n":1,"w":"διὸ","t":"dio","g":"Therefore","s":"G1352","m":"CONJ","l":"διό","lg":"for"},{"n":2,"w":"προσλαμβάνεσθε","t":"proslambanesthe","g":"do receive","s":"G4355","m":"V-PMM-2P","l":"προσλαμβάνω","lg":"to take"},{"n":3,"w":"ἀλλήλους,","t":"allēlous","g":"one another","s":"G0240","m":"C-APM","l":"ἀλλήλων","lg":"one another"},{"n":4,"w":"καθὼς","t":"kathōs","g":"even as","s":"G2531","m":"CONJ","l":"καθώς","lg":"as/just as"},{"n":5,"w":"καὶ","t":"kai","g":"also","s":"G2532","m":"CONJ","l":"καί","lg":"and"},{"n":6,"w":"ὁ","t":"ho","g":"<the>","s":"G3588","m":"T-NSM","l":"ὁ","lg":"the/this/who"},{"n":7,"w":"Χριστὸς","t":"Christos","g":"Christ","s":"G5547","m":"N-NSM-T","l":"Χριστός","lg":"Christ"},{"n":8,"w":"προσελάβετο","t":"proselabeto","g":"received","s":"G4355","m":"V-2AMI-3S","l":"προσλαμβάνω","lg":"to take"},{"n":9,"w":"ὑμᾶς","t":"humas","g":"you","s":"G4771","m":"P-2AP","l":"σύ","lg":"you"},{"n":10,"w":"εἰς","t":"eis","g":"to","s":"G1519","m":"PREP","l":"εἰς","lg":"toward"},{"n":11,"w":"δόξαν","t":"doxan","g":"[the] glory","s":"G1391","m":"N-ASF","l":"δόξα","lg":"glory"},{"n":12,"w":"τοῦ","t":"tou","g":"<the>","s":"G3588","m":"T-GSM","l":"ὁ","lg":"the/this/who"},{"n":13,"w":"θεοῦ.","t":"theou","g":"of God.","s":"G2316","m":"N-GSM-T","l":"θεός","lg":"God"}],"8":[{"n":1,"w":"λέγω","t":"legō","g":"I say","s":"G3004G","m":"V-PAI-1S","l":"λέγω","lg":"to speak"},{"n":2,"w":"γὰρ","t":"gar","g":"for","s":"G1063","m":"CONJ","l":"γάρ","lg":"for"},{"n":3,"w":"Χριστὸν","t":"Christon","g":"Christ","s":"G5547","m":"N-ASM-T","l":"Χριστός","lg":"Christ"},{"n":4,"w":"Ἰησοῦν","t":"Iēsoun","g":"Jesus","s":"G2424G","m":"N-ASM-P","l":"Ἰησοῦς","lg":"Jesus/Joshua"},{"n":5,"w":"διάκονον","t":"diakonon","g":"a servant","s":"G1249","m":"N-ASM","l":"διάκονος","lg":"servant"},{"n":6,"w":"γεγενῆσθαι","t":"gegenēsthai","g":"to have become","s":"G1096","m":"V-RPN","l":"γίνομαι","lg":"to be"},{"n":7,"w":"περιτομῆς","t":"peritomēs","g":"of [the] circumcision","s":"G4061","m":"N-GSF","l":"περιτομή","lg":"circumcision"},{"n":8,"w":"ὑπὲρ","t":"huper","g":"for","s":"G5228","m":"PREP","l":"ὑπέρ","lg":"above/for"},{"n":9,"w":"ἀληθείας","t":"alētheias","g":"[the] truth","s":"G0225","m":"N-GSF","l":"ἀλήθεια","lg":"truth"},{"n":10,"w":"θεοῦ","t":"theou","g":"of God","s":"G2316","m":"N-GSM-T","l":"θεός","lg":"God"},{"n":11,"w":"εἰς","t":"eis","g":"in order","s":"G1519","m":"PREP","l":"εἰς","lg":"toward"},{"n":12,"w":"τὸ","t":"to","g":"<the>","s":"G3588","m":"T-ASN","l":"ὁ","lg":"the/this/who"},{"n":13,"w":"βεβαιῶσαι","t":"bebaiōsai","g":"to confirm","s":"G0950","m":"V-AAN","l":"βεβαιόω","lg":"to confirm"},{"n":14,"w":"τὰς","t":"tas","g":"the","s":"G3588","m":"T-APF","l":"ὁ","lg":"the/this/who"},{"n":15,"w":"ἐπαγγελίας","t":"epangelias","g":"promises given","s":"G1860","m":"N-APF","l":"ἐπαγγελία","lg":"promise"},{"n":16,"w":"τῶν","t":"tōn","g":"to the","s":"G3588","m":"T-GPM","l":"ὁ","lg":"the/this/who"},{"n":17,"w":"πατέρων,","t":"paterōn","g":"fathers,","s":"G3962","m":"N-GPM","l":"πατήρ","lg":"father"}],"9":[{"n":1,"w":"τὰ","t":"ta","g":"<the>","s":"G3588","m":"T-APN","l":"ὁ","lg":"the/this/who"},{"n":2,"w":"δὲ","t":"de","g":"and [for]","s":"G1161","m":"CONJ","l":"δέ","lg":"but/and"},{"n":3,"w":"ἔθνη","t":"ethnē","g":"the Gentiles","s":"G1484","m":"N-APN","l":"ἔθνος","lg":"Gentile nation"},{"n":4,"w":"ὑπὲρ","t":"huper","g":"for","s":"G5228","m":"PREP","l":"ὑπέρ","lg":"above/for"},{"n":5,"w":"ἐλέους","t":"eleous","g":"mercy","s":"G1656","m":"N-GSN","l":"ἔλεος","lg":"mercy"},{"n":6,"w":"δοξάσαι","t":"doxasai","g":"to glorify","s":"G1392","m":"V-AAN","l":"δοξάζω","lg":"to glorify"},{"n":7,"w":"τὸν","t":"ton","g":"<the>","s":"G3588","m":"T-ASM","l":"ὁ","lg":"the/this/who"},{"n":8,"w":"θεὸν","t":"theon","g":"God","s":"G2316","m":"N-ASM-T","l":"θεός","lg":"God"},{"n":9,"w":"καθὼς","t":"kathōs","g":"even as","s":"G2531","m":"CONJ","l":"καθώς","lg":"as/just as"},{"n":10,"w":"γέγραπται·","t":"gegraptai","g":"it has been written:","s":"G1125","m":"V-RPI-3S","l":"γράφω","lg":"to write"},{"n":11,"w":"διὰ","t":"dia","g":"Because of","s":"G1223","m":"PREP","l":"διά","lg":"through/because of"},{"n":12,"w":"τοῦτο","t":"touto","g":"this","s":"G3778","m":"D-ASN","l":"οὗτος","lg":"this/he/she/it"},{"n":13,"w":"ἐξομολογήσομαί","t":"exomologēsomai","g":"I will praise","s":"G1843","m":"V-FMI-1S","l":"ἐξομολογέομαι","lg":"to agree"},{"n":14,"w":"σοι","t":"soi","g":"You","s":"G4771","m":"P-2DS","l":"σύ","lg":"you"},{"n":15,"w":"ἐν","t":"en","g":"among","s":"G1722","m":"PREP","l":"ἐν","lg":"in/on/among"},{"n":16,"w":"ἔθνεσιν","t":"ethnesin","g":"[the] Gentiles","s":"G1484","m":"N-DPN","l":"ἔθνος","lg":"Gentile nation"},{"n":17,"w":"καὶ","t":"kai","g":"and","s":"G2532","m":"CONJ","l":"καί","lg":"and"},{"n":18,"w":"τῷ","t":"tō","g":"to the","s":"G3588","m":"T-DSN","l":"ὁ","lg":"the/this/who"},{"n":19,"w":"ὀνόματί","t":"onomati","g":"name","s":"G3686","m":"N-DSN","l":"ὄνομα","lg":"name"},{"n":20,"w":"σου","t":"sou","g":"of You","s":"G4771","m":"P-2GS","l":"σύ","lg":"you"},{"n":21,"w":"ψαλῶ.","t":"psalō","g":"will I sing.","s":"G5567","m":"V-FAI-1S","l":"ψάλλω","lg":"to sing praise"}],"10":[{"n":1,"w":"καὶ","t":"kai","g":"And","s":"G2532","m":"CONJ","l":"καί","lg":"and"},{"n":2,"w":"πάλιν","t":"palin","g":"again","s":"G3825","m":"ADV","l":"πάλιν","lg":"again"},{"n":3,"w":"λέγει·","t":"legei","g":"it says:","s":"G3004G","m":"V-PAI-3S","l":"λέγω","lg":"to speak"},{"n":4,"w":"εὐφράνθητε","t":"euphranthēte","g":"do rejoice you","s":"G2165","m":"V-APM-2P","l":"εὐφραίνω","lg":"to celebrate"},{"n":5,"w":"ἔθνη","t":"ethnē","g":"Gentiles","s":"G1484","m":"N-VPN","l":"ἔθνος","lg":"Gentile nation"},{"n":6,"w":"μετὰ","t":"meta","g":"with","s":"G3326","m":"PREP","l":"μετά","lg":"with/after"},{"n":7,"w":"τοῦ","t":"tou","g":"the","s":"G3588","m":"T-GSM","l":"ὁ","lg":"the/this/who"},{"n":8,"w":"λαοῦ","t":"laou","g":"people","s":"G2992","m":"N-GSM","l":"λαός","lg":"a people"},{"n":9,"w":"αὐτοῦ.","t":"autou","g":"of Him.","s":"G0846","m":"P-GSM","l":"αὐτός","lg":"he/she/it/self"}],"11":[{"n":1,"w":"καὶ","t":"kai","g":"And","s":"G2532","m":"CONJ","l":"καί","lg":"and"},{"n":2,"w":"πάλιν·","t":"palin","g":"again:","s":"G3825","m":"ADV","l":"πάλιν","lg":"again"},{"n":3,"w":"αἰνεῖτε","t":"aineite","g":"do praise","s":"G0134","m":"V-PAM-2P","l":"αἰνέω","lg":"to praise"},{"n":4,"w":"πάντα","t":"panta","g":"all","s":"G3956","m":"A-VPN","l":"πᾶς","lg":"all"},{"n":5,"w":"τὰ","t":"ta","g":"you who [are]","s":"G3588","m":"T-VPN","l":"ὁ","lg":"the/this/who"},{"n":6,"w":"ἔθνη","t":"ethnē","g":"Gentiles","s":"G1484","m":"N-VPN","l":"ἔθνος","lg":"Gentile nation"},{"n":7,"w":"τὸν","t":"ton","g":"the","s":"G3588","m":"T-ASM","l":"ὁ","lg":"the/this/who"},{"n":8,"w":"κύριον,","t":"kurion","g":"Lord,","s":"G2962G","m":"N-ASM-T","l":"κύριος","lg":"lord"},{"n":9,"w":"καὶ","t":"kai","g":"and","s":"G2532","m":"CONJ","l":"καί","lg":"and"},{"n":10,"w":"ἐπαινεσάτωσαν","t":"epainesatōsan","g":"they should praise","s":"G1867","m":"V-AAM-3P","l":"ἐπαινέω","lg":"to praise"},{"n":11,"w":"αὐτὸν","t":"auton","g":"Him","s":"G0846","m":"P-ASM","l":"αὐτός","lg":"he/she/it/self"},{"n":12,"w":"πάντες","t":"pantes","g":"all","s":"G3956","m":"A-NPM","l":"πᾶς","lg":"all"},{"n":13,"w":"οἱ","t":"hoi","g":"the","s":"G3588","m":"T-NPM","l":"ὁ","lg":"the/this/who"},{"n":14,"w":"λαοί.","t":"laoi","g":"peoples.","s":"G2992","m":"N-NPM","l":"λαός","lg":"a people"}],"12":[{"n":1,"w":"καὶ","t":"kai","g":"And","s":"G2532","m":"CONJ","l":"καί","lg":"and"},{"n":2,"w":"πάλιν","t":"palin","g":"again","s":"G3825","m":"ADV","l":"πάλιν","lg":"again"},{"n":3,"w":"Ἠσαΐας","t":"Ēsaias","g":"Isaiah","s":"G2268","m":"N-NSM-P","l":"Ἡσαΐας","lg":"Isaiah"},{"n":4,"w":"λέγει·","t":"legei","g":"says:","s":"G3004G","m":"V-PAI-3S","l":"λέγω","lg":"to speak"},{"n":5,"w":"ἔσται","t":"estai","g":"There will be","s":"G1510","m":"V-FDI-3S","l":"εἰμί","lg":"to be"},{"n":6,"w":"ἡ","t":"hē","g":"the","s":"G3588","m":"T-NSF","l":"ὁ","lg":"the/this/who"},{"n":7,"w":"ῥίζα","t":"rhiza","g":"root","s":"G4491","m":"N-NSF","l":"ῥίζα","lg":"root"},{"n":8,"w":"τοῦ","t":"tou","g":"<the>","s":"G3588","m":"T-GSM","l":"ὁ","lg":"the/this/who"},{"n":9,"w":"Ἰεσσαί,","t":"Iessai","g":"of Jesse,","s":"G2421","m":"N-GSM-P","l":"Ἰεσσαί","lg":"Jesse"},{"n":10,"w":"καὶ","t":"kai","g":"and","s":"G2532","m":"CONJ","l":"καί","lg":"and"},{"n":11,"w":"ὁ","t":"ho","g":"the [One]","s":"G3588","m":"T-NSM","l":"ὁ","lg":"the/this/who"},{"n":12,"w":"ἀνιστάμενος","t":"anistamenos","g":"arising","s":"G0450","m":"V-PMP-NSM","l":"ἀνίστημι","lg":"to arise"},{"n":13,"w":"ἄρχειν","t":"archein","g":"to rule","s":"G0757","m":"V-PAN","l":"ἄρχω","lg":"be first"},{"n":14,"w":"ἐθνῶν,","t":"ethnōn","g":"over Gentiles,","s":"G1484","m":"N-GPN","l":"ἔθνος","lg":"Gentile nation"},{"n":15,"w":"ἐπ᾽","t":"ep᾽","g":"in","s":"G1909","m":"PREP","l":"ἐπί","lg":"upon/to/against"},{"n":16,"w":"αὐτῷ","t":"autō","g":"Him","s":"G0846","m":"P-DSM","l":"αὐτός","lg":"he/she/it/self"},{"n":17,"w":"ἔθνη","t":"ethnē","g":"[the] Gentiles","s":"G1484","m":"N-NPN","l":"ἔθνος","lg":"Gentile nation"},{"n":18,"w":"ἐλπιοῦσιν.¶","t":"elpiousin","g":"will hope.","s":"G1679","m":"V-FAI-3P","l":"ἐλπίζω","lg":"to hope/expect"}],"13":[{"n":1,"w":"Ὁ","t":"Ho","g":"<the>","s":"G3588","m":"T-NSM","l":"ὁ","lg":"the/this/who"},{"n":2,"w":"δὲ","t":"de","g":"And","s":"G1161","m":"CONJ","l":"δέ","lg":"but/and"},{"n":3,"w":"θεὸς","t":"theos","g":"the God","s":"G2316","m":"N-NSM-T","l":"θεός","lg":"God"},{"n":4,"w":"τῆς","t":"tēs","g":"<the>","s":"G3588","m":"T-GSF","l":"ὁ","lg":"the/this/who"},{"n":5,"w":"ἐλπίδος","t":"elpidos","g":"of hope","s":"G1680","m":"N-GSF","l":"ἐλπίς","lg":"hope"},{"n":6,"w":"πληρώσαι","t":"plērōsai","g":"would fill","s":"G4137","m":"V-AAO-3S","l":"πληρόω","lg":"to fulfill"},{"n":7,"w":"ὑμᾶς","t":"humas","g":"you","s":"G4771","m":"P-2AP","l":"σύ","lg":"you"},{"n":8,"w":"πάσης","t":"pasēs","g":"with all","s":"G3956","m":"A-GSF","l":"πᾶς","lg":"all"},{"n":9,"w":"χαρᾶς","t":"charas","g":"joy","s":"G5479","m":"N-GSF","l":"χαρά","lg":"joy"},{"n":10,"w":"καὶ","t":"kai","g":"and","s":"G2532","m":"CONJ","l":"καί","lg":"and"},{"n":11,"w":"εἰρήνης","t":"eirēnēs","g":"peace","s":"G1515","m":"N-GSF","l":"εἰρήνη","lg":"peace"},{"n":12,"w":"ἐν","t":"en","g":"in","s":"G1722","m":"PREP","l":"ἐν","lg":"in/on/among"},{"n":13,"w":"τῷ","t":"tō","g":"<the>","s":"G3588","m":"T-DSN","l":"ὁ","lg":"the/this/who"},{"n":14,"w":"πιστεύειν","t":"pisteuein","g":"believing","s":"G4100","m":"V-PAN","l":"πιστεύω","lg":"to trust (in)"},{"n":15,"w":"εἰς","t":"eis","g":"for","s":"G1519","m":"PREP","l":"εἰς","lg":"toward"},{"n":16,"w":"τὸ","t":"to","g":"<the>","s":"G3588","m":"T-ASN","l":"ὁ","lg":"the/this/who"},{"n":17,"w":"περισσεύειν","t":"perisseuein","g":"to abound","s":"G4052","m":"V-PAN","l":"περισσεύω","lg":"to abound/exceed"},{"n":18,"w":"ὑμᾶς","t":"humas","g":"you","s":"G4771","m":"P-2AP","l":"σύ","lg":"you"},{"n":19,"w":"ἐν","t":"en","g":"in","s":"G1722","m":"PREP","l":"ἐν","lg":"in/on/among"},{"n":20,"w":"τῇ","t":"tēa","g":"<the>","s":"G3588","m":"T-DSF","l":"ὁ","lg":"the/this/who"},{"n":21,"w":"ἐλπίδι","t":"elpidi","g":"hope","s":"G1680","m":"N-DSF","l":"ἐλπίς","lg":"hope"},{"n":22,"w":"ἐν","t":"en","g":"in","s":"G1722","m":"PREP","l":"ἐν","lg":"in/on/among"},{"n":23,"w":"δυνάμει","t":"dunamei","g":"[the] power","s":"G1411","m":"N-DSF","l":"δύναμις","lg":"power"},{"n":24,"w":"πνεύματος","t":"pneumatos","g":"[of the] Spirit","s":"G4151G","m":"N-GSN","l":"πνεῦμα","lg":"spirit/breath"},{"n":25,"w":"ἁγίου.","t":"hagiou","g":"Holy.","s":"G0040G","m":"A-GSN","l":"ἅγιος","lg":"holy"}],"14":[{"n":1,"w":"πέπεισμαι","t":"pepeismai","g":"I have been persuaded","s":"G3982","m":"V-RPI-1S","l":"πείθω","lg":"to persuade"},{"n":2,"w":"δέ,","t":"de","g":"now,","s":"G1161","m":"CONJ","l":"δέ","lg":"but/and"},{"n":3,"w":"ἀδελφοί","t":"adelphoi","g":"brothers","s":"G0080","m":"N-VPM","l":"ἀδελφός","lg":"brother"},{"n":4,"w":"μου,","t":"mou","g":"of mine,","s":"G3165","m":"P-1GS","l":"ἐγώ","lg":"I/we"},{"n":5,"w":"καὶ","t":"kai","g":"also","s":"G2532","m":"CONJ","l":"καί","lg":"and"},{"n":6,"w":"αὐτὸς","t":"autos","g":"myself","s":"G0846","m":"P-NSM","l":"αὐτός","lg":"he/she/it/self"},{"n":7,"w":"ἐγὼ","t":"egō","g":"I myself","s":"G1473","m":"P-1NS","l":"ἐγώ","lg":"I/we"},{"n":8,"w":"περὶ","t":"peri","g":"concerning","s":"G4012","m":"PREP","l":"περί","lg":"about"},{"n":9,"w":"ὑμῶν","t":"humōn","g":"you","s":"G4771","m":"P-2GP","l":"σύ","lg":"you"},{"n":10,"w":"ὅτι","t":"hoti","g":"that","s":"G3754G","m":"CONJ","l":"ὅτι","lg":"that/since"},{"n":11,"w":"καὶ","t":"kai","g":"also","s":"G2532","m":"CONJ","l":"καί","lg":"and"},{"n":12,"w":"αὐτοὶ","t":"autoi","g":"you yourselves","s":"G0846","m":"P-NPM","l":"αὐτός","lg":"he/she/it/self"},{"n":13,"w":"μεστοί","t":"mestoi","g":"full","s":"G3324","m":"A-NPM","l":"μεστός","lg":"full"},{"n":14,"w":"ἐστε","t":"este","g":"are","s":"G1510","m":"V-PAI-2P","l":"εἰμί","lg":"to be"},{"n":15,"w":"ἀγαθωσύνης","t":"agathōsunēs","g":"of goodness","s":"G0019","m":"N-GSF","l":"ἀγαθωσύνη","lg":"goodness"},{"n":16,"w":"πεπληρωμένοι","t":"peplērōmenoi","g":"filled","s":"G4137","m":"V-RPP-NPM","l":"πληρόω","lg":"to fulfill"},{"n":17,"w":"πάσης","t":"pasēs","g":"with all","s":"G3956","m":"A-GSF","l":"πᾶς","lg":"all"},{"n":18,"w":"τῆς","t":"tēs","g":"<the>","s":"G3588","m":"T-GSF","l":"ὁ","lg":"the/this/who"},{"n":19,"w":"γνώσεως,","t":"gnōseōs","g":"knowledge,","s":"G1108","m":"N-GSF","l":"γνῶσις","lg":"knowledge"},{"n":20,"w":"δυνάμενοι","t":"dunamenoi","g":"being able","s":"G1410","m":"V-PNP-NPM","l":"δύναμαι","lg":"be able"},{"n":21,"w":"καὶ","t":"kai","g":"also","s":"G2532","m":"CONJ","l":"καί","lg":"and"},{"n":22,"w":"ἀλλήλους","t":"allēlous","g":"one another","s":"G0240","m":"C-APM","l":"ἀλλήλων","lg":"one another"},{"n":23,"w":"νουθετεῖν.¶","t":"nouthetein","g":"to admonish.","s":"G3560","m":"V-PAN","l":"νουθετέω","lg":"to admonish"}],"15":[{"n":1,"w":"Τολμηρότερον","t":"Tolmēroteron","g":"More boldly","s":"G5112","m":"ADV-C","l":"τολμηρότερον","lg":"more boldly"},{"n":2,"w":"δὲ","t":"de","g":"however","s":"G1161","m":"CONJ","l":"δέ","lg":"but/and"},{"n":3,"w":"ἔγραψα","t":"egrapsa","g":"I have written","s":"G1125","m":"V-2AAI-1S","l":"γράφω","lg":"to write"},{"n":4,"w":"ὑμῖν","t":"humin","g":"to you","s":"G4771","m":"P-2DP","l":"σύ","lg":"you"},{"n":5,"w":"ἀδελφοί","t":"adelphoi","g":"brothers","s":"G0080","m":"N-VPM","l":"ἀδελφός","lg":"brother"},{"n":6,"w":"ἀπὸ","t":"apo","g":"in","s":"G0575","m":"PREP","l":"ἀπό","lg":"away from"},{"n":7,"w":"μέρους","t":"merous","g":"part","s":"G3313","m":"N-GSN","l":"μέρος","lg":"part"},{"n":8,"w":"ὡς","t":"hōs","g":"as","s":"G5613","m":"PRT","l":"ὡς","lg":"which/how"},{"n":9,"w":"ἐπαναμιμνῄσκων","t":"epanamimnēskōn","g":"reminding","s":"G1878","m":"V-PAP-NSM","l":"ἐπαναμιμνῄσκω","lg":"to remind"},{"n":10,"w":"ὑμᾶς","t":"humas","g":"you","s":"G4771","m":"P-2AP","l":"σύ","lg":"you"},{"n":11,"w":"διὰ","t":"dia","g":"because of","s":"G1223","m":"PREP","l":"διά","lg":"through/because of"},{"n":12,"w":"τὴν","t":"tēn","g":"the","s":"G3588","m":"T-ASF","l":"ὁ","lg":"the/this/who"},{"n":13,"w":"χάριν","t":"charin","g":"grace","s":"G5485","m":"N-ASF","l":"χάρις","lg":"grace"},{"n":14,"w":"τὴν","t":"tēn","g":"which","s":"G3588","m":"T-ASF","l":"ὁ","lg":"the/this/who"},{"n":15,"w":"δοθεῖσάν","t":"dotheisan","g":"having been given","s":"G1325","m":"V-APP-ASF","l":"δίδωμι","lg":"to give"},{"n":16,"w":"μοι","t":"moi","g":"to me","s":"G3165","m":"P-1DS","l":"ἐγώ","lg":"I/we"},{"n":17,"w":"ὑπὸ","t":"hupo","g":"by","s":"G5259G","m":"PREP","l":"ὑπό","lg":"by/under"},{"n":18,"w":"τοῦ","t":"tou","g":"<the>","s":"G3588","m":"T-GSM","l":"ὁ","lg":"the/this/who"},{"n":19,"w":"θεοῦ","t":"theou","g":"God","s":"G2316","m":"N-GSM-T","l":"θεός","lg":"God"}],"16":[{"n":1,"w":"εἰς","t":"eis","g":"for","s":"G1519","m":"PREP","l":"εἰς","lg":"toward"},{"n":2,"w":"τὸ","t":"to","g":"<the>","s":"G3588","m":"T-ASN","l":"ὁ","lg":"the/this/who"},{"n":3,"w":"εἶναί","t":"einai","g":"to be","s":"G1511","m":"V-PAN","l":"εἰμί","lg":"to be"},{"n":4,"w":"με","t":"me","g":"me","s":"G3165","m":"P-1AS","l":"ἐγώ","lg":"I/we"},{"n":5,"w":"λειτουργὸν","t":"leitourgon","g":"a minister","s":"G3011","m":"N-ASM","l":"λειτουργός","lg":"minister"},{"n":6,"w":"Χριστοῦ","t":"Christou","g":"of Christ","s":"G5547","m":"N-GSM-T","l":"Χριστός","lg":"Christ"},{"n":7,"w":"Ἰησοῦ","t":"Iēsou","g":"Jesus","s":"G2424G","m":"N-GSM-P","l":"Ἰησοῦς","lg":"Jesus/Joshua"},{"n":8,"w":"εἰς","t":"eis","g":"to","s":"G1519","m":"PREP","l":"εἰς","lg":"toward"},{"n":9,"w":"τὰ","t":"ta","g":"the","s":"G3588","m":"T-APN","l":"ὁ","lg":"the/this/who"},{"n":10,"w":"ἔθνη","t":"ethnē","g":"Gentiles","s":"G1484","m":"N-APN","l":"ἔθνος","lg":"Gentile nation"},{"n":11,"w":"ἱερουργοῦντα","t":"hi'erourgounta","g":"administering the sacred service","s":"G2418","m":"V-PAP-ASM","l":"ἱερουργέω","lg":"to minister"},{"n":12,"w":"τὸ","t":"to","g":"of the","s":"G3588","m":"T-ASN","l":"ὁ","lg":"the/this/who"},{"n":13,"w":"εὐαγγέλιον","t":"euangelion","g":"gospel","s":"G2098","m":"N-ASN","l":"εὐαγγέλιον","lg":"gospel"},{"n":14,"w":"τοῦ","t":"tou","g":"<the>","s":"G3588","m":"T-GSM","l":"ὁ","lg":"the/this/who"},{"n":15,"w":"θεοῦ,","t":"theou","g":"of God,","s":"G2316","m":"N-GSM-T","l":"θεός","lg":"God"},{"n":16,"w":"ἵνα","t":"ina","g":"so that","s":"G2443","m":"CONJ","l":"ἵνα","lg":"in order that/to"},{"n":17,"w":"γένηται","t":"genētai","g":"may become","s":"G1096","m":"V-2ADS-3S","l":"γίνομαι","lg":"to be"},{"n":18,"w":"ἡ","t":"hē","g":"the","s":"G3588","m":"T-NSF","l":"ὁ","lg":"the/this/who"},{"n":19,"w":"προσφορὰ","t":"prosphora","g":"offering","s":"G4376","m":"N-NSF","l":"προσφορά","lg":"offering"},{"n":20,"w":"τῶν","t":"tōn","g":"of the","s":"G3588","m":"T-GPN","l":"ὁ","lg":"the/this/who"},{"n":21,"w":"ἐθνῶν","t":"ethnōn","g":"Gentiles","s":"G1484","m":"N-GPN","l":"ἔθνος","lg":"Gentile nation"},{"n":22,"w":"εὐπρόσδεκτος","t":"euprosdektos","g":"acceptable","s":"G2144","m":"A-NSF","l":"εὐπρόσδεκτος","lg":"acceptable"},{"n":23,"w":"ἡγιασμένη","t":"hēgiasmenē","g":"sanctified","s":"G0037","m":"V-RPP-NSF","l":"ἁγιάζω","lg":"to sanctify"},{"n":24,"w":"ἐν","t":"en","g":"in [the]","s":"G1722","m":"PREP","l":"ἐν","lg":"in/on/among"},{"n":25,"w":"πνεύματι","t":"pneumati","g":"Spirit","s":"G4151G","m":"N-DSN","l":"πνεῦμα","lg":"spirit/breath"},{"n":26,"w":"ἁγίῳ.¶","t":"hagiō","g":"Holy.","s":"G0040G","m":"A-DSN","l":"ἅγιος","lg":"holy"}],"17":[{"n":1,"w":"Ἔχω","t":"Echō","g":"I have","s":"G2192","m":"V-PAI-1S","l":"ἔχω","lg":"to have/be"},{"n":2,"w":"οὖν","t":"oun","g":"therefore","s":"G3767","m":"CONJ","l":"οὖν","lg":"therefore/then"},{"n":3,"w":"τὴν","t":"tēn","g":"the","s":"G3588","m":"T-ASF","l":"ὁ","lg":"the/this/who"},{"n":4,"w":"καύχησιν","t":"kauchēsin","g":"boasting","s":"G2746","m":"N-ASF","l":"καύχησις","lg":"pride"},{"n":5,"w":"ἐν","t":"en","g":"in","s":"G1722","m":"PREP","l":"ἐν","lg":"in/on/among"},{"n":6,"w":"Χριστῷ","t":"Christō","g":"Christ","s":"G5547","m":"N-DSM-T","l":"Χριστός","lg":"Christ"},{"n":7,"w":"Ἰησοῦ","t":"Iēsou","g":"Jesus","s":"G2424G","m":"N-DSM-P","l":"Ἰησοῦς","lg":"Jesus/Joshua"},{"n":8,"w":"τὰ","t":"ta","g":"the [things]","s":"G3588","m":"T-APN","l":"ὁ","lg":"the/this/who"},{"n":9,"w":"πρὸς","t":"pros","g":"pertaining to","s":"G4314","m":"PREP","l":"πρός","lg":"to/with"},{"n":10,"w":"τὸν","t":"ton","g":"<the>","s":"G3588","m":"T-ASM","l":"ὁ","lg":"the/this/who"},{"n":11,"w":"θεόν·","t":"theon","g":"God;","s":"G2316","m":"N-ASM-T","l":"θεός","lg":"God"}],"18":[{"n":1,"w":"οὐ","t":"ou","g":"Not","s":"G3756","m":"PRT-N","l":"οὐ","lg":"no"},{"n":2,"w":"γὰρ","t":"gar","g":"for","s":"G1063","m":"CONJ","l":"γάρ","lg":"for"},{"n":3,"w":"τολμήσω","t":"tolmēsō","g":"will I dare","s":"G5111","m":"V-FAI-1S","l":"τολμάω","lg":"be bold"},{"n":4,"w":"τι","t":"ti","g":"anything","s":"G5100","m":"X-ASN","l":"τις","lg":"one"},{"n":5,"w":"λαλεῖν","t":"lalein","g":"to speak","s":"G2980","m":"V-PAN","l":"λαλέω","lg":"to speak"},{"n":6,"w":"ὧν","t":"hōn","g":"of what","s":"G3739","m":"R-GPN","l":"ὅς, ἥ","lg":"which"},{"n":7,"w":"οὐ","t":"ou","g":"except","s":"G3756","m":"PRT-N","l":"οὐ","lg":"no"},{"n":8,"w":"κατειργάσατο","t":"kateirgasato","g":"has accomplished","s":"G2716","m":"V-ADI-3S","l":"κατεργάζομαι","lg":"to workout/produce"},{"n":9,"w":"Χριστὸς","t":"Christos","g":"Christ","s":"G5547","m":"N-NSM-T","l":"Χριστός","lg":"Christ"},{"n":10,"w":"δι᾽","t":"di᾽","g":"through","s":"G1223","m":"PREP","l":"διά","lg":"through/because of"},{"n":11,"w":"ἐμοῦ","t":"emou","g":"me","s":"G1473","m":"S-1SGSN","l":"ἐγώ","lg":"I/we"},{"n":12,"w":"εἰς","t":"eis","g":"unto [the]","s":"G1519","m":"PREP","l":"εἰς","lg":"toward"},{"n":13,"w":"ὑπακοὴν","t":"hupakoēn","g":"obedience","s":"G5218","m":"N-ASF","l":"ὑπακοή","lg":"obedience"},{"n":14,"w":"ἐθνῶν","t":"ethnōn","g":"of [the] Gentiles","s":"G1484","m":"N-GPN","l":"ἔθνος","lg":"Gentile nation"},{"n":15,"w":"λόγῳ","t":"logō","g":"by word","s":"G3056","m":"N-DSM","l":"λόγος","lg":"word"},{"n":16,"w":"καὶ","t":"kai","g":"and","s":"G2532","m":"CONJ","l":"καί","lg":"and"},{"n":17,"w":"ἔργῳ,","t":"ergō","g":"by deed,","s":"G2041","m":"N-DSN","l":"ἔργον","lg":"work"}],"19":[{"n":1,"w":"ἐν","t":"en","g":"in [the]","s":"G1722","m":"PREP","l":"ἐν","lg":"in/on/among"},{"n":2,"w":"δυνάμει","t":"dunamei","g":"power","s":"G1411","m":"N-DSF","l":"δύναμις","lg":"power"},{"n":3,"w":"σημείων","t":"sēmeiōn","g":"of signs","s":"G4592","m":"N-GPN","l":"σημεῖον","lg":"sign"},{"n":4,"w":"καὶ","t":"kai","g":"and","s":"G2532","m":"CONJ","l":"καί","lg":"and"},{"n":5,"w":"τεράτων,","t":"teratōn","g":"wonders,","s":"G5059","m":"N-GPN","l":"τέρας","lg":"wonders"},{"n":6,"w":"ἐν","t":"en","g":"in [the]","s":"G1722","m":"PREP","l":"ἐν","lg":"in/on/among"},{"n":7,"w":"δυνάμει","t":"dunamei","g":"power","s":"G1411","m":"N-DSF","l":"δύναμις","lg":"power"},{"n":8,"w":"πνεύματος","t":"pneumatos","g":"of [the] Spirit","s":"G4151G","m":"N-GSN","l":"πνεῦμα","lg":"spirit/breath"},{"n":9,"w":"θεοῦ,","t":"theou","g":"of God,","s":"G2316","m":"N-GSM-T","l":"θεός","lg":"God"},{"n":10,"w":"ὥστε","t":"hōste","g":"so as","s":"G5620","m":"CONJ","l":"ὥστε","lg":"so"},{"n":11,"w":"με","t":"me","g":"for me","s":"G3165","m":"P-1AS","l":"ἐγώ","lg":"I/we"},{"n":12,"w":"ἀπὸ","t":"apo","g":"from","s":"G0575","m":"PREP","l":"ἀπό","lg":"away from"},{"n":13,"w":"Ἰερουσαλὴμ","t":"Ierousalēm","g":"Jerusalem","s":"G2419","m":"N-GSF-L","l":"Ἱερουσαλήμ","lg":"Jerusalem"},{"n":14,"w":"καὶ","t":"kai","g":"and","s":"G2532","m":"CONJ","l":"καί","lg":"and"},{"n":15,"w":"κύκλῳ","t":"kuklō","g":"around","s":"G2945","m":"ADV","l":"κύκλῳ","lg":"surrounding"},{"n":16,"w":"μέχρι","t":"mechri","g":"unto","s":"G3360","m":"PREP","l":"μέχρι","lg":"until"},{"n":17,"w":"τοῦ","t":"tou","g":"<the>","s":"G3588","m":"T-GSN","l":"ὁ","lg":"the/this/who"},{"n":18,"w":"Ἰλλυρικοῦ","t":"Illurikou","g":"Illyricum","s":"G2437","m":"N-GSN-L","l":"Ἰλλυρικόν","lg":"Illyricum"},{"n":19,"w":"πεπληρωκέναι","t":"peplērōkenai","g":"to have fully proclaimed","s":"G4137","m":"V-RAN","l":"πληρόω","lg":"to fulfill"},{"n":20,"w":"τὸ","t":"to","g":"the","s":"G3588","m":"T-ASN","l":"ὁ","lg":"the/this/who"},{"n":21,"w":"εὐαγγέλιον","t":"euangelion","g":"gospel","s":"G2098","m":"N-ASN","l":"εὐαγγέλιον","lg":"gospel"},{"n":22,"w":"τοῦ","t":"tou","g":"<the>","s":"G3588","m":"T-GSM","l":"ὁ","lg":"the/this/who"},{"n":23,"w":"Χριστοῦ.","t":"Christou","g":"of Christ.","s":"G5547","m":"N-GSM-T","l":"Χριστός","lg":"Christ"}],"20":[{"n":1,"w":"οὕτως","t":"houtōs","g":"thus","s":"G3779","m":"ADV","l":"οὕτω, οὕτως","lg":"thus(-ly)"},{"n":2,"w":"δὲ","t":"de","g":"now","s":"G1161","m":"CONJ","l":"δέ","lg":"but/and"},{"n":3,"w":"φιλοτιμούμενον","t":"philotimoumenon","g":"being ambitious","s":"G5389","m":"V-PNP-ASM","l":"φιλοτιμέομαι","lg":"to aspire"},{"n":4,"w":"εὐαγγελίζεσθαι","t":"euangelizesthai","g":"to evangelise","s":"G2097","m":"V-PMN","l":"εὐαγγελίζομαι","lg":"to speak good news"},{"n":5,"w":"οὐχ","t":"ouch","g":"not","s":"G3756","m":"PRT-N","l":"οὐ","lg":"no"},{"n":6,"w":"ὅπου","t":"hopou","g":"where","s":"G3699","m":"CONJ","l":"ὅπου","lg":"where(-ever)"},{"n":7,"w":"ὠνομάσθη","t":"ōnomasthē","g":"was named","s":"G3687","m":"V-API-3S","l":"ὀνομάζω","lg":"to name"},{"n":8,"w":"Χριστός,","t":"Christos","g":"Christ,","s":"G5547","m":"N-NSM-T","l":"Χριστός","lg":"Christ"},{"n":9,"w":"ἵνα","t":"ina","g":"so that","s":"G2443","m":"CONJ","l":"ἵνα","lg":"in order that/to"},{"n":10,"w":"μὴ","t":"mē","g":"not","s":"G3361","m":"PRT-N","l":"μή","lg":"not"},{"n":11,"w":"ἐπ᾽","t":"ep᾽","g":"upon","s":"G1909","m":"PREP","l":"ἐπί","lg":"upon/to/against"},{"n":12,"w":"ἀλλότριον","t":"allotrion","g":"another’s","s":"G0245","m":"A-ASM","l":"ἀλλότριος","lg":"another’s"},{"n":13,"w":"θεμέλιον","t":"themelion","g":"foundation","s":"G2310","m":"N-ASM","l":"θεμέλιος","lg":"foundation"},{"n":14,"w":"οἰκοδομῶ","t":"oikodomō","g":"I may build","s":"G3618","m":"V-PAS-1S","l":"οἰκοδομέω","lg":"to build"}],"21":[{"n":1,"w":"ἀλλὰ","t":"alla","g":"Rather","s":"G0235","m":"CONJ","l":"ἀλλά","lg":"but"},{"n":2,"w":"καθὼς","t":"kathōs","g":"even as","s":"G2531","m":"CONJ","l":"καθώς","lg":"as/just as"},{"n":3,"w":"γέγραπται·","t":"gegraptai","g":"it has been written:","s":"G1125","m":"V-RPI-3S","l":"γράφω","lg":"to write"},{"n":4,"w":"οἷς","t":"hois","g":"To whom","s":"G3739","m":"R-DPM","l":"ὅς, ἥ","lg":"which"},{"n":5,"w":"οὐκ","t":"ouk","g":"not","s":"G3756","m":"PRT-N","l":"οὐ","lg":"no"},{"n":6,"w":"ἀνηγγέλη","t":"anēngelē","g":"it was proclaimed","s":"G0312","m":"V-2API-3S","l":"ἀναγγέλλω","lg":"to report"},{"n":7,"w":"περὶ","t":"peri","g":"concerning","s":"G4012","m":"PREP","l":"περί","lg":"about"},{"n":8,"w":"αὐτοῦ","t":"autou","g":"Him","s":"G0846","m":"P-GSM","l":"αὐτός","lg":"he/she/it/self"},{"n":9,"w":"ὄψονται","t":"opsontai","g":"they will behold","s":"G3700G","m":"V-FDI-3P","l":"ὁράω","lg":"to see"},{"n":10,"w":"καὶ","t":"kai","g":"and","s":"G2532","m":"CONJ","l":"καί","lg":"and"},{"n":11,"w":"οἳ","t":"hoi","g":"those that","s":"G3739","m":"R-NPM","l":"ὅς, ἥ","lg":"which"},{"n":12,"w":"οὐκ","t":"ouk","g":"not","s":"G3756","m":"PRT-N","l":"οὐ","lg":"no"},{"n":13,"w":"ἀκηκόασιν","t":"akēkoasin","g":"have heard","s":"G0191","m":"V-2RAI-3P","l":"ἀκούω","lg":"to hear"},{"n":14,"w":"συνήσουσιν.","t":"sunēsousin","g":"will understand.","s":"G4920","m":"V-FAI-3P","l":"συνίημι","lg":"to understand"}],"22":[{"n":1,"w":"διὸ","t":"dio","g":"Therefore","s":"G1352","m":"CONJ","l":"διό","lg":"for"},{"n":2,"w":"καὶ","t":"kai","g":"also","s":"G2532","m":"CONJ","l":"καί","lg":"and"},{"n":3,"w":"ἐνεκοπτόμην","t":"enekoptomēn","g":"I was being hindered","s":"G1465","m":"V-IPI-1S","l":"ἐγκόπτω","lg":"to impede"},{"n":4,"w":"τὰ","t":"ta","g":"<the>","s":"G3588","m":"T-APN","l":"ὁ","lg":"the/this/who"},{"n":5,"w":"πολλὰ","t":"polla","g":"many [times]","s":"G4183","m":"A-APN","l":"πολύς","lg":"much"},{"n":6,"w":"τοῦ","t":"tou","g":"<the>","s":"G3588","m":"T-GSN","l":"ὁ","lg":"the/this/who"},{"n":7,"w":"ἐλθεῖν","t":"elthein","g":"to come","s":"G2064","m":"V-2AAN","l":"ἔρχομαι","lg":"to come/go"},{"n":8,"w":"πρὸς","t":"pros","g":"to","s":"G4314","m":"PREP","l":"πρός","lg":"to/with"},{"n":9,"w":"ὑμᾶς,","t":"humas","g":"you,","s":"G4771","m":"P-2AP","l":"σύ","lg":"you"}],"23":[{"n":1,"w":"νυνὶ","t":"nuni","g":"Now","s":"G3570","m":"ADV","l":"νυνί","lg":"now"},{"n":2,"w":"δὲ","t":"de","g":"however","s":"G1161","m":"CONJ","l":"δέ","lg":"but/and"},{"n":3,"w":"μηκέτι","t":"mēketi","g":"no longer","s":"G3371","m":"ADV-N","l":"μηκέτι","lg":"never again"},{"n":4,"w":"τόπον","t":"topon","g":"a place","s":"G5117","m":"N-ASM","l":"τόπος","lg":"place"},{"n":5,"w":"ἔχων","t":"echōn","g":"having","s":"G2192","m":"V-PAP-NSM","l":"ἔχω","lg":"to have/be"},{"n":6,"w":"ἐν","t":"en","g":"in","s":"G1722","m":"PREP","l":"ἐν","lg":"in/on/among"},{"n":7,"w":"τοῖς","t":"tois","g":"<the>","s":"G3588","m":"T-DPN","l":"ὁ","lg":"the/this/who"},{"n":8,"w":"κλίμασιν","t":"klimasin","g":"regions","s":"G2824","m":"N-DPN","l":"κλίμα","lg":"region"},{"n":9,"w":"τούτοις","t":"toutois","g":"these","s":"G3778","m":"D-DPN","l":"οὗτος","lg":"this/he/she/it"},{"n":10,"w":"ἐπιποθίαν","t":"epipothian","g":"a great desire","s":"G1974","m":"N-ASF","l":"ἐπιποθία","lg":"longing"},{"n":11,"w":"δὲ","t":"de","g":"now","s":"G1161","m":"CONJ","l":"δέ","lg":"but/and"},{"n":12,"w":"ἔχων","t":"echōn","g":"having had","s":"G2192","m":"V-PAP-NSM","l":"ἔχω","lg":"to have/be"},{"n":13,"w":"τοῦ","t":"tou","g":"<the>","s":"G3588","m":"T-GSN","l":"ὁ","lg":"the/this/who"},{"n":14,"w":"ἐλθεῖν","t":"elthein","g":"to come","s":"G2064","m":"V-2AAN","l":"ἔρχομαι","lg":"to come/go"},{"n":15,"w":"πρὸς","t":"pros","g":"to","s":"G4314","m":"PREP","l":"πρός","lg":"to/with"},{"n":16,"w":"ὑμᾶς","t":"humas","g":"you","s":"G4771","m":"P-2AP","l":"σύ","lg":"you"},{"n":17,"w":"ἀπὸ","t":"apo","g":"for","s":"G0575","m":"PREP","l":"ἀπό","lg":"away from"},{"n":18,"w":"πολλῶν","t":"pollōn","g":"many","s":"G4183","m":"A-GPN","l":"πολύς","lg":"much"},{"n":19,"w":"ἐτῶν,","t":"etōn","g":"years,","s":"G2094","m":"N-GPN","l":"ἔτος","lg":"year"}],"24":[{"n":1,"w":"ὡς","t":"hōs","g":"whenever","s":"G5613","m":"PRT","l":"ὡς","lg":"which/how"},{"n":2,"w":"ἂν","t":"an","g":"maybe","s":"G0302","m":"PRT","l":"ἄν","lg":"if"},{"n":3,"w":"πορεύωμαι","t":"poreuōmai","g":"I shall go","s":"G4198","m":"V-PNS-1S","l":"πορεύω","lg":"to travel"},{"n":4,"w":"εἰς","t":"eis","g":"to","s":"G1519","m":"PREP","l":"εἰς","lg":"toward"},{"n":5,"w":"τὴν","t":"tēn","g":"<the>","s":"G3588","m":"T-ASF","l":"ὁ","lg":"the/this/who"},{"n":6,"w":"Σπανίαν","t":"Spanian","g":"Spain","s":"G4681","m":"N-ASF-L","l":"Σπανία","lg":"Spain"},{"n":7,"w":"ἐλεύσομαι","t":"eleusomai","g":"I will come","s":"G2064","m":"V-FDI-1S","l":"ἔρχομαι","lg":"to come/go"},{"n":8,"w":"πρὸς","t":"pros","g":"to","s":"G4314","m":"PREP","l":"πρός","lg":"to/with"},{"n":9,"w":"ὑμᾶς,","t":"humas","g":"you","s":"G4771","m":"P-2AP","l":"σύ","lg":"you"},{"n":10,"w":"ἐλπίζω","t":"elpizō","g":"I hope","s":"G1679","m":"V-PAI-1S","l":"ἐλπίζω","lg":"to hope/expect"},{"n":11,"w":"γὰρ","t":"gar","g":"for","s":"G1063","m":"CONJ","l":"γάρ","lg":"for"},{"n":12,"w":"διαπορευόμενος","t":"diaporeuomenos","g":"going through","s":"G1279","m":"V-PNP-NSM","l":"διαπορεύω","lg":"to travel through"},{"n":13,"w":"θεάσασθαι","t":"theasasthai","g":"to see","s":"G2300","m":"V-ADN","l":"θεάομαι","lg":"to look at"},{"n":14,"w":"ὑμᾶς","t":"humas","g":"you","s":"G4771","m":"P-2AP","l":"σύ","lg":"you"},{"n":15,"w":"καὶ","t":"kai","g":"and","s":"G2532","m":"CONJ","l":"καί","lg":"and"},{"n":16,"w":"ὑφ᾽","t":"huph᾽","g":"by","s":"G5259G","m":"PREP","l":"ὑπό","lg":"by/under"},{"n":17,"w":"ὑμῶν","t":"humōn","g":"you","s":"G4771","m":"P-2GP","l":"σύ","lg":"you"},{"n":18,"w":"προπεμφθῆναι","t":"propemphthēnai","g":"to be equipped","s":"G4311","m":"V-APN","l":"προπέμπω","lg":"to help on the way"},{"n":19,"w":"ἐκεῖ,","t":"ekei","g":"there,","s":"G1563","m":"ADV","l":"ἐκεῖ","lg":"there"},{"n":20,"w":"ἐὰν","t":"ean","g":"if","s":"G1437","m":"COND","l":"ἐάν","lg":"if"},{"n":21,"w":"ὑμῶν","t":"humōn","g":"of you","s":"G4771","m":"P-2GP","l":"σύ","lg":"you"},{"n":22,"w":"πρῶτον","t":"prōton","g":"first","s":"G4413H","m":"A-ASN","l":"πρῶτος","lg":"first"},{"n":23,"w":"ἀπὸ","t":"apo","g":"in","s":"G0575","m":"PREP","l":"ἀπό","lg":"away from"},{"n":24,"w":"μέρους","t":"merous","g":"part","s":"G3313","m":"N-GSN","l":"μέρος","lg":"part"},{"n":25,"w":"ἐμπλησθῶ.¶","t":"emplēsthō","g":"I shall be filled.","s":"G1705","m":"V-APS-1S","l":"ἐμπίμπλημι","lg":"to fill up"}],"25":[{"n":1,"w":"Νυνὶ","t":"Nuni","g":"Now","s":"G3570","m":"ADV","l":"νυνί","lg":"now"},{"n":2,"w":"δὲ","t":"de","g":"however","s":"G1161","m":"CONJ","l":"δέ","lg":"but/and"},{"n":3,"w":"πορεύομαι","t":"poreuomai","g":"I am going","s":"G4198","m":"V-PNI-1S","l":"πορεύω","lg":"to travel"},{"n":4,"w":"εἰς","t":"eis","g":"to","s":"G1519","m":"PREP","l":"εἰς","lg":"toward"},{"n":5,"w":"Ἰερουσαλὴμ","t":"Ierousalēm","g":"Jerusalem","s":"G2419","m":"N-ASF-L","l":"Ἱερουσαλήμ","lg":"Jerusalem"},{"n":6,"w":"διακονῶν","t":"diakonōn","g":"ministering","s":"G1247","m":"V-PAP-NSM","l":"διακονέω","lg":"to serve"},{"n":7,"w":"τοῖς","t":"tois","g":"to the","s":"G3588","m":"T-DPM","l":"ὁ","lg":"the/this/who"},{"n":8,"w":"ἁγίοις.","t":"hagiois","g":"saints.","s":"G0040H","m":"A-DPM","l":"ἅγιος","lg":"holy"}],"26":[{"n":1,"w":"εὐδόκησαν","t":"eudokēsan","g":"Were pleased","s":"G2106","m":"V-AAI-3P","l":"εὐδοκέω","lg":"to delight"},{"n":2,"w":"γὰρ","t":"gar","g":"for","s":"G1063","m":"CONJ","l":"γάρ","lg":"for"},{"n":3,"w":"Μακεδονία","t":"Makedonia","g":"Macedonia","s":"G3109","m":"N-NSF-L","l":"Μακεδονία","lg":"Macedonia"},{"n":4,"w":"καὶ","t":"kai","g":"and","s":"G2532","m":"CONJ","l":"καί","lg":"and"},{"n":5,"w":"Ἀχαΐα","t":"Achaia","g":"Achaia","s":"G0882","m":"N-NSF-L","l":"Ἀχαΐα","lg":"Achaia"},{"n":6,"w":"κοινωνίαν","t":"koinōnian","g":"a contribution","s":"G2842","m":"N-ASF","l":"κοινωνία","lg":"participation"},{"n":7,"w":"τινὰ","t":"tina","g":"certain","s":"G5100","m":"X-ASF","l":"τις","lg":"one"},{"n":8,"w":"ποιήσασθαι","t":"poiēsasthai","g":"to make","s":"G4160G","m":"V-AMN","l":"ποιέω","lg":"to do/make"},{"n":9,"w":"εἰς","t":"eis","g":"for","s":"G1519","m":"PREP","l":"εἰς","lg":"toward"},{"n":10,"w":"τοὺς","t":"tous","g":"the","s":"G3588","m":"T-APM","l":"ὁ","lg":"the/this/who"},{"n":11,"w":"πτωχοὺς","t":"ptōchous","g":"poor","s":"G4434","m":"N-APM","l":"πτωχός","lg":"poor"},{"n":12,"w":"τῶν","t":"tōn","g":"among the","s":"G3588","m":"T-GPM","l":"ὁ","lg":"the/this/who"},{"n":13,"w":"ἁγίων","t":"hagiōn","g":"saints","s":"G0040H","m":"A-GPM","l":"ἅγιος","lg":"holy"},{"n":14,"w":"τῶν","t":"tōn","g":"<the>","s":"G3588","m":"T-GPM","l":"ὁ","lg":"the/this/who"},{"n":15,"w":"ἐν","t":"en","g":"in","s":"G1722","m":"PREP","l":"ἐν","lg":"in/on/among"},{"n":16,"w":"Ἰερουσαλήμ·","t":"Ierousalēm","g":"Jerusalem;","s":"G2419","m":"N-DSF-L","l":"Ἱερουσαλήμ","lg":"Jerusalem"}],"27":[{"n":1,"w":"εὐδόκησαν","t":"eudokēsan","g":"They were pleased","s":"G2106","m":"V-AAI-3P","l":"εὐδοκέω","lg":"to delight"},{"n":2,"w":"γάρ,","t":"gar","g":"for,","s":"G1063","m":"CONJ","l":"γάρ","lg":"for"},{"n":3,"w":"καὶ","t":"kai","g":"and","s":"G2532","m":"CONJ","l":"καί","lg":"and"},{"n":4,"w":"ὀφειλέται","t":"opheiletai","g":"debtors","s":"G3781","m":"N-NPM","l":"ὀφειλέτης","lg":"debtor"},{"n":5,"w":"εἰσὶν","t":"eisin","g":"they are","s":"G1510","m":"V-PAI-3P","l":"εἰμί","lg":"to be"},{"n":6,"w":"αὐτῶν·","t":"autōn","g":"of them;","s":"G0846","m":"P-GPM","l":"αὐτός","lg":"he/she/it/self"},{"n":7,"w":"εἰ","t":"ei","g":"If","s":"G1487G","m":"COND","l":"εἰ","lg":"if"},{"n":8,"w":"γὰρ","t":"gar","g":"for","s":"G1063","m":"CONJ","l":"γάρ","lg":"for"},{"n":9,"w":"τοῖς","t":"tois","g":"in the [things]","s":"G3588","m":"T-DPN","l":"ὁ","lg":"the/this/who"},{"n":10,"w":"πνευματικοῖς","t":"pneumatikois","g":"spiritual","s":"G4152","m":"A-DPN","l":"πνευματικός","lg":"spiritual"},{"n":11,"w":"αὐτῶν","t":"autōn","g":"of them","s":"G0846","m":"P-GPM","l":"αὐτός","lg":"he/she/it/self"},{"n":12,"w":"ἐκοινώνησαν","t":"ekoinōnēsan","g":"shared","s":"G2841","m":"V-AAI-3P","l":"κοινωνέω","lg":"to participate"},{"n":13,"w":"τὰ","t":"ta","g":"the","s":"G3588","m":"T-NPN","l":"ὁ","lg":"the/this/who"},{"n":14,"w":"ἔθνη,","t":"ethnē","g":"Gentiles,","s":"G1484","m":"N-NPN","l":"ἔθνος","lg":"Gentile nation"},{"n":15,"w":"ὀφείλουσιν","t":"opheilousin","g":"they ought","s":"G3784","m":"V-PAI-3P","l":"ὀφείλω","lg":"to owe"},{"n":16,"w":"καὶ","t":"kai","g":"also","s":"G2532","m":"CONJ","l":"καί","lg":"and"},{"n":17,"w":"ἐν","t":"en","g":"in","s":"G1722","m":"PREP","l":"ἐν","lg":"in/on/among"},{"n":18,"w":"τοῖς","t":"tois","g":"the","s":"G3588","m":"T-DPN","l":"ὁ","lg":"the/this/who"},{"n":19,"w":"σαρκικοῖς","t":"sarkikois","g":"material things","s":"G4559","m":"A-DPN","l":"σαρκικός","lg":"fleshly"},{"n":20,"w":"λειτουργῆσαι","t":"leitourgēsai","g":"to minister","s":"G3008","m":"V-AAN","l":"λειτουργέω","lg":"to minister"},{"n":21,"w":"αὐτοῖς.","t":"autois","g":"to them.","s":"G0846","m":"P-DPM","l":"αὐτός","lg":"he/she/it/self"}],"28":[{"n":1,"w":"τοῦτο","t":"touto","g":"This","s":"G3778","m":"D-ASN","l":"οὗτος","lg":"this/he/she/it"},{"n":2,"w":"οὖν","t":"oun","g":"therefore","s":"G3767","m":"CONJ","l":"οὖν","lg":"therefore/then"},{"n":3,"w":"ἐπιτελέσας","t":"epitelesas","g":"having finished","s":"G2005","m":"V-AAP-NSM","l":"ἐπιτελέω","lg":"to complete"},{"n":4,"w":"καὶ","t":"kai","g":"and","s":"G2532","m":"CONJ","l":"καί","lg":"and"},{"n":5,"w":"σφραγισάμενος","t":"sphragisamenos","g":"having sealed","s":"G4972","m":"V-AMP-NSM","l":"σφραγίζω","lg":"to seal"},{"n":6,"w":"αὐτοῖς","t":"autois","g":"to them","s":"G0846","m":"P-DPM","l":"αὐτός","lg":"he/she/it/self"},{"n":7,"w":"τὸν","t":"ton","g":"<the>","s":"G3588","m":"T-ASM","l":"ὁ","lg":"the/this/who"},{"n":8,"w":"καρπὸν","t":"karpon","g":"fruit","s":"G2590","m":"N-ASM","l":"καρπός","lg":"fruit"},{"n":9,"w":"τοῦτον","t":"touton","g":"this","s":"G3778","m":"D-ASM","l":"οὗτος","lg":"this/he/she/it"},{"n":10,"w":"ἀπελεύσομαι","t":"apeleusomai","g":"I will set off","s":"G0565","m":"V-FDI-1S","l":"ἀπέρχομαι","lg":"to go away"},{"n":11,"w":"δι᾽","t":"di᾽","g":"through","s":"G1223","m":"PREP","l":"διά","lg":"through/because of"},{"n":12,"w":"ὑμῶν","t":"humōn","g":"you","s":"G4771","m":"P-2GP","l":"σύ","lg":"you"},{"n":13,"w":"εἰς","t":"eis","g":"into","s":"G1519","m":"PREP","l":"εἰς","lg":"toward"},{"n":14,"w":"τὴν","t":"tēn","g":"<the>","s":"G3588","m":"T-ASF","l":"ὁ","lg":"the/this/who"},{"n":15,"w":"Σπανίαν.","t":"Spanian","g":"Spain.","s":"G4681","m":"N-ASF-L","l":"Σπανία","lg":"Spain"}],"29":[{"n":1,"w":"οἶδα","t":"oida","g":"I know","s":"G6063","m":"V-RAI-1S","l":"εἴδω","lg":"to perceive"},{"n":2,"w":"δὲ","t":"de","g":"now","s":"G1161","m":"CONJ","l":"δέ","lg":"but/and"},{"n":3,"w":"ὅτι","t":"hoti","g":"that","s":"G3754G","m":"CONJ","l":"ὅτι","lg":"that/since"},{"n":4,"w":"ἐρχόμενος","t":"erchomenos","g":"coming","s":"G2064","m":"V-PNP-NSM","l":"ἔρχομαι","lg":"to come/go"},{"n":5,"w":"πρὸς","t":"pros","g":"to","s":"G4314","m":"PREP","l":"πρός","lg":"to/with"},{"n":6,"w":"ὑμᾶς","t":"humas","g":"you","s":"G4771","m":"P-2AP","l":"σύ","lg":"you"},{"n":7,"w":"ἐν","t":"en","g":"in","s":"G1722","m":"PREP","l":"ἐν","lg":"in/on/among"},{"n":8,"w":"πληρώματι","t":"plērōmati","g":"[the] fullness","s":"G4138","m":"N-DSN","l":"πλήρωμα","lg":"fulfillment"},{"n":9,"w":"εὐλογίας","t":"eulogias","g":"of the blessing","s":"G2129","m":"N-GSF","l":"εὐλογία","lg":"praise"},{"n":10,"w":"τοῦ","t":"tou","g":"of the","s":"G3588","m":"T-GSN","l":"ὁ","lg":"the/this/who"},{"n":11,"w":"εὐαγγελίου","t":"euangeliou","g":"gospel","s":"G2098","m":"N-GSN","l":"εὐαγγέλιον","lg":"gospel"},{"n":12,"w":"τοῦ","t":"tou","g":"<the>","s":"G3588","m":"T-GSM","l":"ὁ","lg":"the/this/who"},{"n":13,"w":"Χριστοῦ","t":"Christou","g":"of Christ","s":"G5547","m":"N-GSM-T","l":"Χριστός","lg":"Christ"},{"n":14,"w":"ἐλεύσομαι.¶","t":"eleusomai","g":"I will come.","s":"G2064","m":"V-FDI-1S","l":"ἔρχομαι","lg":"to come/go"}],"30":[{"n":1,"w":"Παρακαλῶ","t":"Parakalō","g":"I exhort","s":"G3870","m":"V-PAI-1S","l":"παρακαλέω","lg":"to plead/comfort"},{"n":2,"w":"δὲ","t":"de","g":"now","s":"G1161","m":"CONJ","l":"δέ","lg":"but/and"},{"n":3,"w":"ὑμᾶς,","t":"humas","g":"you,","s":"G4771","m":"P-2AP","l":"σύ","lg":"you"},{"n":4,"w":"ἀδελφοί,","t":"adelphoi","g":"brothers,","s":"G0080","m":"N-VPM","l":"ἀδελφός","lg":"brother"},{"n":5,"w":"διὰ","t":"dia","g":"through","s":"G1223","m":"PREP","l":"διά","lg":"through/because of"},{"n":6,"w":"τοῦ","t":"tou","g":"the","s":"G3588","m":"T-GSM","l":"ὁ","lg":"the/this/who"},{"n":7,"w":"κυρίου","t":"kuriou","g":"Lord","s":"G2962G","m":"N-GSM-T","l":"κύριος","lg":"lord"},{"n":8,"w":"ἡμῶν","t":"hēmōn","g":"of us","s":"G3165","m":"P-1GP","l":"ἐγώ","lg":"I/we"},{"n":9,"w":"Ἰησοῦ","t":"Iēsou","g":"Jesus","s":"G2424G","m":"N-GSM-P","l":"Ἰησοῦς","lg":"Jesus/Joshua"},{"n":10,"w":"Χριστοῦ","t":"Christou","g":"Christ","s":"G5547","m":"N-GSM-T","l":"Χριστός","lg":"Christ"},{"n":11,"w":"καὶ","t":"kai","g":"and","s":"G2532","m":"CONJ","l":"καί","lg":"and"},{"n":12,"w":"διὰ","t":"dia","g":"through","s":"G1223","m":"PREP","l":"διά","lg":"through/because of"},{"n":13,"w":"τῆς","t":"tēs","g":"the","s":"G3588","m":"T-GSF","l":"ὁ","lg":"the/this/who"},{"n":14,"w":"ἀγάπης","t":"agapēs","g":"love","s":"G0026","m":"N-GSF","l":"ἀγάπη","lg":"love"},{"n":15,"w":"τοῦ","t":"tou","g":"of the","s":"G3588","m":"T-GSN","l":"ὁ","lg":"the/this/who"},{"n":16,"w":"πνεύματος,","t":"pneumatos","g":"Spirit,","s":"G4151G","m":"N-GSN","l":"πνεῦμα","lg":"spirit/breath"},{"n":17,"w":"συναγωνίσασθαί","t":"sunagōnisasthai","g":"to strive together with","s":"G4865","m":"V-AMN","l":"συναγωνίζομαι","lg":"to struggle"},{"n":18,"w":"μοι","t":"moi","g":"me","s":"G3165","m":"P-1DS","l":"ἐγώ","lg":"I/we"},{"n":19,"w":"ἐν","t":"en","g":"in","s":"G1722","m":"PREP","l":"ἐν","lg":"in/on/among"},{"n":20,"w":"ταῖς","t":"tais","g":"the","s":"G3588","m":"T-DPF","l":"ὁ","lg":"the/this/who"},{"n":21,"w":"προσευχαῖς","t":"proseuchais","g":"prayers","s":"G4335","m":"N-DPF","l":"προσευχή","lg":"prayer"},{"n":22,"w":"ὑπὲρ","t":"huper","g":"for","s":"G5228","m":"PREP","l":"ὑπέρ","lg":"above/for"},{"n":23,"w":"ἐμοῦ","t":"emou","g":"me","s":"G1473","m":"S-1SGSN","l":"ἐγώ","lg":"I/we"},{"n":24,"w":"πρὸς","t":"pros","g":"to","s":"G4314","m":"PREP","l":"πρός","lg":"to/with"},{"n":25,"w":"τὸν","t":"ton","g":"<the>","s":"G3588","m":"T-ASM","l":"ὁ","lg":"the/this/who"},{"n":26,"w":"θεόν,","t":"theon","g":"God,","s":"G2316","m":"N-ASM-T","l":"θεός","lg":"God"}],"31":[{"n":1,"w":"ἵνα","t":"ina","g":"so that","s":"G2443","m":"PREP","l":"ἵνα","lg":"in order that/to"},{"n":2,"w":"ῥυσθῶ","t":"rhusthō","g":"I may be delivered","s":"G4506","m":"V-APS-1S","l":"ῥύομαι","lg":"to deliver"},{"n":3,"w":"ἀπὸ","t":"apo","g":"from","s":"G0575","m":"PREP","l":"ἀπό","lg":"away from"},{"n":4,"w":"τῶν","t":"tōn","g":"those","s":"G3588","m":"T-GPM","l":"ὁ","lg":"the/this/who"},{"n":5,"w":"ἀπειθούντων","t":"apeithountōn","g":"refusing to be persuaded","s":"G0544","m":"V-PAP-GPM","l":"ἀπειθέω","lg":"to disobey"},{"n":6,"w":"ἐν","t":"en","g":"in","s":"G1722","m":"PREP","l":"ἐν","lg":"in/on/among"},{"n":7,"w":"τῇ","t":"tēa","g":"<the>","s":"G3588","m":"T-DSF","l":"ὁ","lg":"the/this/who"},{"n":8,"w":"Ἰουδαίᾳ","t":"Ioudaia","g":"Judea","s":"G2449","m":"N-DSF-L","l":"Ἰουδαία","lg":"Judea"},{"n":9,"w":"καὶ","t":"kai","g":"and","s":"G2532","m":"CONJ","l":"καί","lg":"and"},{"n":10,"w":"ἵνα","t":"ina","g":"so that","s":"G2443","m":"CONJ","l":"ἵνα","lg":"in order that/to"},{"n":11,"w":"ἡ","t":"hē","g":"the","s":"G3588","m":"T-NSF","l":"ὁ","lg":"the/this/who"},{"n":12,"w":"διακονία","t":"diakonia","g":"service","s":"G1248","m":"N-NSF","l":"διακονία","lg":"service"},{"n":13,"w":"μου","t":"mou","g":"of mine","s":"G3165","m":"P-1GS","l":"ἐγώ","lg":"I/we"},{"n":14,"w":"ἡ","t":"hē","g":"which [is]","s":"G3588","m":"T-NSF","l":"ὁ","lg":"the/this/who"},{"n":15,"w":"εἰς","t":"eis","g":"in","s":"G1519","m":"PREP","l":"εἰς","lg":"toward"},{"n":16,"w":"Ἰερουσαλὴμ","t":"Ierousalēm","g":"Jerusalem","s":"G2419","m":"N-ASF-L","l":"Ἱερουσαλήμ","lg":"Jerusalem"},{"n":17,"w":"εὐπρόσδεκτος","t":"euprosdektos","g":"acceptable","s":"G2144","m":"A-NSF","l":"εὐπρόσδεκτος","lg":"acceptable"},{"n":18,"w":"τοῖς","t":"tois","g":"to the","s":"G3588","m":"T-DPM","l":"ὁ","lg":"the/this/who"},{"n":19,"w":"ἁγίοις","t":"hagiois","g":"saints","s":"G0040H","m":"A-DPM","l":"ἅγιος","lg":"holy"},{"n":20,"w":"γένηται,","t":"genētai","g":"may become","s":"G1096","m":"V-2ADS-3S","l":"γίνομαι","lg":"to be"}],"32":[{"n":1,"w":"ἵνα","t":"ina","g":"so that","s":"G2443","m":"CONJ","l":"ἵνα","lg":"in order that/to"},{"n":2,"w":"ἐν","t":"en","g":"in","s":"G1722","m":"PREP","l":"ἐν","lg":"in/on/among"},{"n":3,"w":"χαρᾷ","t":"chara","g":"joy","s":"G5479","m":"N-DSF","l":"χαρά","lg":"joy"},{"n":4,"w":"ἐλθὼν","t":"elthōn","g":"having come","s":"G2064","m":"V-2AAP-NSM","l":"ἔρχομαι","lg":"to come/go"},{"n":5,"w":"πρὸς","t":"pros","g":"to","s":"G4314","m":"PREP","l":"πρός","lg":"to/with"},{"n":6,"w":"ὑμᾶς","t":"humas","g":"you","s":"G4771","m":"P-2AP","l":"σύ","lg":"you"},{"n":7,"w":"διὰ","t":"dia","g":"through","s":"G1223","m":"PREP","l":"διά","lg":"through/because of"},{"n":8,"w":"θελήματος","t":"thelēmatos","g":"[the] will","s":"G2307","m":"N-GSN","l":"θέλημα","lg":"will/desire"},{"n":9,"w":"θεοῦ","t":"theou","g":"of God","s":"G2316","m":"N-GSM-T","l":"θεός","lg":"God"},{"n":10,"w":"καὶ","t":"kai","g":"and","s":"G2532","m":"CONJ","l":"καί","lg":"and"},{"n":11,"w":"συναναπαύσωμαι","t":"sunanapausōmai","g":"I may be refreshed with","s":"G4875","m":"V-ADS-1S","l":"συναναπαύομαι","lg":"to rest with"},{"n":12,"w":"ὑμῖν.","t":"humin","g":"you.","s":"G4771","m":"P-2DP","l":"σύ","lg":"you"}],"33":[{"n":1,"w":"ὁ","t":"ho","g":"<the>","s":"G3588","m":"T-NSM","l":"ὁ","lg":"the/this/who"},{"n":2,"w":"δὲ","t":"de","g":"And","s":"G1161","m":"CONJ","l":"δέ","lg":"but/and"},{"n":3,"w":"θεὸς","t":"theos","g":"the God","s":"G2316","m":"N-NSM-T","l":"θεός","lg":"God"},{"n":4,"w":"τῆς","t":"tēs","g":"<the>","s":"G3588","m":"T-GSF","l":"ὁ","lg":"the/this/who"},{"n":5,"w":"εἰρήνης","t":"eirēnēs","g":"of peace","s":"G1515","m":"N-GSF","l":"εἰρήνη","lg":"peace"},{"n":6,"w":"μετὰ","t":"meta","g":"[be] with","s":"G3326","m":"PREP","l":"μετά","lg":"with/after"},{"n":7,"w":"πάντων","t":"pantōn","g":"all","s":"G3956","m":"A-GPM","l":"πᾶς","lg":"all"},{"n":8,"w":"ὑμῶν,","t":"humōn","g":"of you,","s":"G4771","m":"P-2GP","l":"σύ","lg":"you"},{"n":9,"w":"ἀμήν.¶","t":"amēn","g":"Amen.","s":"G0281","m":"INJ-HEB","l":"ἀμήν","lg":"amen"}]}